Workbook

Sheet README
A1: Test Case Design Sheet v1.1
A2: Project | B2: Playwright QA Automation for Insurance Order Entry Platform (Whole Life), application on port 8081. Submission 2: Test Design.
A3: What changed in v1.1 | B3: Reconciled with: the mentor/learner answers to Q-01..Q-17, the Lab Manual (users, URLs, API key header), and constants read from the application source (routes, config, seed data, markup test ids). All 81 tests and their priorities are kept (Q-16). See Change_Log for details.
A4: Basis codes | B4: M = Lab Manual. S = application source (constants, config, seed data, markup). A = learner answer. D = Functional / Problem documents. V = to verify at first run. Source-derived values are expectations to CONFIRM in the running UI, not a replacement for the business documents.
A5: Black-box note | B5: The Lab Manual says to treat both apps as black boxes. The source was used only for constants and selectors. Expected results still come from the functional documents; any difference found at run time is a finding, not a test change.
A7: Sheets | B7: Test_Cases (81) | Test_Data | Calculators (premium and affordability, live formulas) | Environment_Facts (confirmed facts) | Locator_Map (data-testid per page) | Traceability_Risk | Traceability_SDC | Coverage_Summary | Open_Items | Change_Log
A8: Edit these cells | B8: Yellow cells: Execution status, Defect ID, Defect type, Notes (Test_Cases); Official catalog ID (Traceability_SDC); Status (Open_Items). Blue numbers on Calculators and Coverage_Summary are inputs.
A9: Do not rename | B9: Module names, Risk IDs and SDC IDs are used by COUNTIF formulas; keep them exactly, separated by "; ".
A10: Credentials | B10: Usernames only appear in this workbook. Passwords and the API key are read from .env (INSURANCE_PASSWORD, INSURANCE_API_KEY) and are never written into tests, reports or submissions (Lab Manual section 13).
A11: Example row | B11: Row 2 of Test_Cases (TC-AUTH-001) shows the expected level of detail.
A13: Key definitions
A14: Priority | B14: P1 = covers a P1 risk or is a smoke test; P2 = P2 risk; P3 = lower. "Priority basis" names the risk that sets it (Q-16).
A15: Automation status | B15: Ready = all facts known, build now. Needs confirmation = one item in "Remaining open items" must be checked at first run. Automated / Manual only are set while building.
A16: Defect type (if Fail) | B16: Q-17: report both. Expected seeded (candidate) = matches an SDC row; Unexpected = anything else; plus Automation issue and Environment/data so failures are classified before logging.
A17: UI selectors / API contract | B17: data-testid values that exist in the build, or the API call and its response envelope. Use these instead of guessing locators.
A18: Same-agent rule | B18: The API acts as learner001 unless agent_email is passed. Every UI-vs-API comparison must pass agent_email equal to the logged-in UI user.

Sheet Test_Cases
A1: TC ID | B1: Module | C1: Validation ID | D1: Scenario | E1: Risk ID(s) | F1: Seeded defect candidate(s) | G1: Layer | H1: Test type | I1: Priority | J1: Priority basis | K1: Tags | L1: Preconditions | M1: Test data | N1: Test steps | O1: Expected result | P1: UI selectors / API contract | Q1: Page object / helper | R1: Evidence expectation | S1: Remaining open items | T1: Source basis | U1: Automation status | V1: Execution status | W1: Defect ID | X1: Defect type (if Fail) | Y1: Notes
A2: TC-AUTH-001 | B2: Authentication | C2: AUTH-V01 | D2: Valid agent can log in successfully | E2: R-AUTH-01 | F2: SDC-01 | G2: UI | H2: Smoke | I2: P1 | J2: Smoke test; highest linked risk R-AUTH-01 (score 9) | K2: @smoke @regression @authentication @SDC-01 | L2: Application reachable. No active session (fresh browser context). | M2: {validAgent} = agent.valid@insurance.test (password from .env) | N2: 1. Open /login. 2. Fill login-email-input and login-password-input. 3. Click login-submit-button. | O2: - URL is /dashboard (not /login). - dashboard-page is visible with the agent's applications. - No error alert. | P2: /login: login-email-input, login-password-input, login-submit-button; then dashboard-page | Q2: LoginPage, DashboardPage | R2: Screenshot of dashboard greeting; trace on failure. | T2: M, S | U2: Ready | V2: Not run
A3: TC-AUTH-002 | B3: Authentication | C3: AUTH-V02 | D3: Invalid password displays the correct error message | E3: R-AUTH-05 | G3: UI | H3: Smoke | I3: P1 | J3: Smoke test; highest linked risk R-AUTH-05 (score 4) | K3: @smoke @regression @authentication | L3: No active session. | M3: {validAgent} username + wrong password "Wrong#Pass123" | N3: 1. Open /login. 2. Enter valid username and the wrong password. 3. Click sign in. | O3: - User stays on /login. - Invalid-credentials error is displayed (capture exact text on first run). - No session; /dashboard redirects to /login. | P3: login-form, validation-error-alert / status-alert | Q3: LoginPage | R3: Screenshot of error message. | T3: M, S | U3: Ready | V3: Not run
A4: TC-AUTH-003 | B4: Authentication | C4: AUTH-V03 | D4: Blank username and password show mandatory validation | E4: R-AUTH-05 | G4: UI | H4: Negative | I4: P3 | J4: highest linked risk R-AUTH-05 (score 4) | K4: @regression @authentication | L4: No active session. | M4: Empty username and password | N4: 1. Open /login. 2. Leave both fields empty and click sign in. 3. Repeat with only username filled, then only password filled. | O4: - Field-level mandatory errors appear for each empty field. - User stays on /login. - No successful login; no session created. | P4: login-form (browser "required" or server validation: capture which) | Q4: LoginPage | R4: Screenshot of field-level errors. | T4: D, S | U4: Ready | V4: Not run
A5: TC-AUTH-004 | B5: Authentication | C5: AUTH-V04 | D5: Logout clears the session and redirects to login | E5: R-AUTH-06 | G5: UI | H5: Authorization | I5: P2 | J5: highest linked risk R-AUTH-06 (score 6) | K5: @regression @authentication | L5: Agent is logged in on /dashboard. | M5: {validAgent} | N5: 1. Log in, then store the session cookie value. 2. Click nav-logout-button. 3. Assert redirect to /login. 4. Navigate to /dashboard (and use browser Back). 5. Open a new request context carrying the pre-logout session cookie and GET /dashboard. | O5: - Logout lands on /login. - /dashboard redirects to /login. - The old session cookie no longer gives access (redirect to /login). | P5: nav-logout-button; /login; /dashboard | Q5: LoginPage, DashboardPage, apiClient | R5: Screenshot of /login after back navigation; API status code attached. | T5: S | U5: Ready | V5: Not run
A6: TC-AUTH-005 | B6: Authentication | C6: AUTH-V05 | D6: Direct access to dashboard without login is blocked | E6: R-AUTH-06 | G6: UI | H6: Smoke | I6: P1 | J6: Smoke test; highest linked risk R-AUTH-06 (score 6) | K6: @smoke @regression @authentication | L6: Fresh browser context with no storage state. | M6: None | N6: 1. In a fresh context open /dashboard. 2. Repeat for /applications, /applications/new, /profile, /support. 3. Repeat for /applications/{id}/client using a real application id. | O6: - Each request ends on /login. - No protected content is rendered. | P6: Routes behind auth middleware: /dashboard, /applications, /applications/new, /profile, /support | Q6: LoginPage | R6: Screenshot and final URL for each route. | T6: S | U6: Ready | V6: Not run
A7: TC-AUTH-006 | B7: Authentication | C7: AUTH-V06 | D7: Locked user cannot access the dashboard | E7: R-AUTH-02 | F7: SDC-02 | G7: UI + API | H7: Negative | I7: P2 | J7: highest linked risk R-AUTH-02 (score 6) | K7: @regression @api @authentication @SDC-02 | L7: Seeded locked user exists. | M7: {lockedAgent} = agent.locked@insurance.test with correct password | N7: 1. Sign in through /login as {lockedAgent}. 2. Read the message shown. 3. Try to open /dashboard. 4. POST /api/login with the same credentials. | O7: - Account-locked message (not the generic invalid-password message). Capture exact text. - /dashboard is not accessible. - API returns 403, status "error", message "Account locked", errors.account_status present. | P7: UI /login message; API POST /api/login (X-API-Key) | Q7: LoginPage, apiClient | R7: Screenshot of lock message; API response body. | T7: M, S | U7: Ready | V7: Not run
A8: TC-AUTH-007 | B8: Authentication | C8: AUTH-V07 | D8: Account locks after five failed login attempts | E8: R-AUTH-03 | G8: UI + API | H8: Boundary | I8: P2 | J8: highest linked risk R-AUTH-03 (score 6) | K8: @regression @api @authentication | L8: Spare learner-pool account {disposableAgent} on your own VM (confirm with mentor). DESTRUCTIVE. Lock is time-based (locked_until); run LAST in a serial project. | M8: {disposableAgent} with wrong password x5, then correct password | N8: 1. Attempt 1 to 4 with a wrong password; after each, record the message. 2. Attempt 5 with a wrong password. 3. Attempt 6 with the CORRECT password. 4. Read lock flag through API/DB if available. | O8: - Attempts 1-4: invalid-credentials message, account not locked. - Attempt 5: account locked. - Attempt 6 with the correct password is denied until the lock expires. - Record lock duration seen (locked_until) for the report. | P8: login form; users.failed_login_attempts / locked_until (DB columns) | Q8: LoginPage, apiClient | R8: Screenshot after attempts 4, 5 and 6; run note that user needs reset. | S8: OI-14 | T8: D, S | U8: Needs confirmation | V8: Not run
A9: TC-AUTH-008 | B9: Authentication | C9: AUTH-V08 | D9: Password policy rejects weak passwords | E9: R-AUTH-04 | F9: SDC-03 | G9: UI | H9: Negative | I9: P2 | J9: highest linked risk R-AUTH-04 (score 6) | K9: @regression @authentication @SDC-03 | L9: Logged in as {disposableAgent}. Only REJECTED values are submitted, so the password is never changed. (No API endpoint exists for password change.) | M9: TD-PWD-01 table (rule-by-rule weak values) | N9: 1. Open /change-password. 2. For each weak value in TD-PWD-01 enter it as the new password (and matching confirmation) and submit. 3. Read the message(s). 4. Check the strength indicator for a compliant example without submitting it. | O9: - Every weak value is rejected with the message for the broken rule (12+ chars, upper, lower, digit, one of !@#$%^&*, no email username, no common/sequential pattern, no 3 repeated characters). - Password is unchanged (original still logs in). | P9: /change-password: change-password-current, change-password-new, change-password-confirm, change-password-submit, change-password-strength | Q9: LoginPage, apiClient | R9: Screenshot per rejected value (parameterised report). | T9: S | U9: Ready | V9: Not run
A10: TC-DASH-001 | B10: Dashboard & application summary | C10: DASH-V01 | D10: Dashboard loads after successful login | E10: R-DASH-04 | G10: UI | H10: Smoke | I10: P1 | J10: Smoke test; highest linked risk R-DASH-04 (score 4) | K10: @smoke @regression @dashboard | L10: Valid agent logged in. | M10: {validAgent} | N10: 1. Log in (auth fixture). 2. Open /dashboard. 3. Observe summary cards and application list. | O10: - Summary cards (draft, submitted, under review, approved, requires info) are visible. - dashboard-new-application-button is enabled. - dashboard-applications-table is rendered. | P10: dashboard-page, dashboard-summary-draft/-submitted/-under-review/-approved/-requires-info, dashboard-new-application-button, dashboard-applications-table | Q10: DashboardPage | R10: Screenshot of dashboard. | T10: S | U10: Ready | V10: Not run
A11: TC-DASH-002 | B11: Dashboard & application summary | C11: DASH-V02 | D11: Agent sees only their own applications | E11: R-DASH-01 | G11: UI + API | H11: Authorization | I11: P2 | J11: highest linked risk R-DASH-01 (score 6) | K11: @regression @api @dashboard | L11: Two agents each own at least one application. | M11: {validAgent} (agent.valid) and {agent2} (agent.draft) | N11: 1. Log in as {validAgent}; collect application ids from /applications. 2. Log in as {agent2}; collect ids. 3. Compare the sets. 4. GET /api/applications?agent_email=<each agent> and compare with the UI lists. 5. As {validAgent} open /applications/{id} of an application owned by {agent2}. | O11: - The two id sets do not overlap. - UI list equals API list for each agent (same agent_email as the UI user). - Opening another agent's application in the UI is denied (403). | P11: application-row-*, application-open-{id}; API GET /api/applications?agent_email= | Q11: DashboardPage, apiClient | R11: Both ID lists attached to the report. | T11: S | U11: Ready | V11: Not run
A12: TC-DASH-003 | B12: Dashboard & application summary | C12: DASH-V03 | D12: New agent sees empty application state | E12: R-DASH-04 | G12: UI + API | H12: Functional | I12: P3 | J12: highest linked risk R-DASH-04 (score 4) | K12: @regression @api @dashboard | L12: Seeded new agent with no applications. | M12: {newAgent} = agent.new@insurance.test | N12: 1. Log in as {newAgent}. 2. Observe dashboard. 3. Call GET /api/applications. | O12: - Empty-state message and Start New Application CTA are shown. - Draft and submitted counts are zero. - API returns an empty list. | P12: dashboard-empty-state; GET /api/applications?agent_email=agent.new@insurance.test | Q12: DashboardPage, apiClient | R12: Screenshot of empty state. | T12: M, S | U12: Ready | V12: Not run
A13: TC-DASH-004 | B13: Dashboard & application summary | C13: DASH-V04 | D13: Draft application can be resumed from the dashboard | E13: R-DASH-03 | F13: SDC-16 | G13: UI | H13: Functional | I13: P2 | J13: highest linked risk R-DASH-03 (score 6) | K13: @regression @dashboard @SDC-16 | L13: A draft exists with known client data (created by the test). | M13: Draft with first name QA_<runId>, DOB = today - 40y | N13: 1. Create a draft with client data and save it. 2. Return to /dashboard. 3. Click Resume on that draft row. 4. Inspect the client form. | O13: - The application opened has the same ID as the clicked row. - Previously entered values are present in the form. - Status remains Draft. | P13: application-open-{id}; resume lands on the step stored in current_step | Q13: DashboardPage, ClientInformationPage | R13: Screenshot of resumed form. | T13: S | U13: Ready | V13: Not run
A14: TC-DASH-005 | B14: Dashboard & application summary | C14: DASH-V05 | D14: Application status filter and summary counts work correctly | E14: R-DASH-04 | G14: UI + API | H14: Functional | I14: P3 | J14: highest linked risk R-DASH-04 (score 4) | K14: @regression @api @dashboard | L14: Agent with DRAFT and SUBMITTED applications: use {submittedAgent} (agent.submitted) plus a draft created by the test. Approved is out of scope (Q-15). | M14: {validAgent} | N14: 1. Read the dashboard summary counts for Draft, Submitted, Requires info. 2. If a filter control exists on /dashboard or /applications, apply Draft then Submitted and read the rows; otherwise note "no UI filter". 3. GET /api/applications?agent_email=...&status=DRAFT and =SUBMITTED. 4. Compare. | O14: - Summary counts equal the API counts per status. - Any UI filter shows only rows of the chosen status. - API ?status= returns only that status. - If no UI filter exists, record it as an observation against DASH-V05. | P14: dashboard-summary-*; API GET /api/applications?agent_email=&status=DRAFT|SUBMITTED | Q14: DashboardPage, apiClient | R14: Screenshot per filter state. | S14: OI-15 | T14: S, V | U14: Needs confirmation | V14: Not run
A15: TC-DASH-006 | B15: Dashboard & application summary | C15: DASH-V06 | D15: Dashboard status matches the application status API | E15: R-DASH-02 | F15: SDC-18 | G15: UI + API | H15: Reconciliation | I15: P1 | J15: highest linked risk R-DASH-02 (score 9) | K15: @regression @api @dashboard @SDC-18 | L15: Agent owns at least one Draft and one Submitted application. | M15: {learnerUser} (same account used for UI and agent_email) | N15: 1. Log in as {learnerUser}; read application-status-{id} for each row. 2. GET /api/applications?agent_email=<same learner> and GET /api/applications/{id}/status. 3. Compare per id. | O15: - Dashboard status equals list API status and status API application_status for every id. - Comparison uses the same agent on both sides. | P15: application-status-{id}; GET /api/applications?agent_email=; GET /api/applications/{id}/status | Q15: DashboardPage, apiClient | R15: Table of id / UI status / API status attached. | T15: S | U15: Ready | V15: Not run
A16: TC-CLI-001 | B16: Client / insured information | C16: CLI-V01 | D16: Agent can enter valid insured personal information | E16: R-CLI-03; R-CLI-05 | G16: UI | H16: Smoke | I16: P1 | J16: Smoke test; highest linked risk R-CLI-05 (score 6) | K16: @smoke @regression @client | L16: Logged in as {validAgent}; new application started. | M16: Applicant age 40; gender MALE/FEMALE/NON_BINARY; marital SINGLE/MARRIED/DIVORCED/WIDOWED; all mandatory fields filled | N16: 1. Log in; open /applications/new and click application-create-draft-button. 2. Fill every client field. 3. Click client-save-continue-button. | O16: - Redirect to /applications/{id}/address-contact. - Success message "Client information saved." is shown. - GET /api/applications/{id}/client returns the entered values. | P16: client-first-name-input, client-middle-name-input, client-last-name-input, client-dob-input, client-gender-select, client-marital-status-select, client-nationality-input, client-occupation-input, client-employer-name-input, client-employer-address-input, client-save-continue-button | Q16: DashboardPage, ClientInformationPage | R16: Screenshot of completed form. | T16: S | U16: Ready | V16: Not run
A17: TC-CLI-002 | B17: Client / insured information | C17: CLI-V02 | D17: Mandatory personal fields are validated | E17: R-CLI-03 | G17: UI | H17: Negative | I17: P3 | J17: highest linked risk R-CLI-03 (score 4) | K17: @regression @client | L17: New application on the client step. | M17: Mandatory: first name, last name, DOB, gender, marital status, nationality, occupation, employer name, employer address. Middle name is optional. | N17: 1. Fill all fields with valid data. 2. Clear one mandatory field. 3. Try to continue. 4. Repeat for each mandatory field. | O17: - Inline error appears beside the blank field. - Next is disabled or blocked. - Other fields keep their values. | P17: client-first-name-input, client-middle-name-input, client-last-name-input, client-dob-input, client-gender-select, client-marital-status-select, client-nationality-input, client-occupation-input, client-employer-name-input, client-employer-address-input, client-save-continue-button | Q17: ClientInformationPage | R17: Screenshot per field iteration. | T17: D, S | U17: Ready | V17: Not run
A18: TC-CLI-003 | B18: Client / insured information | C18: CLI-V03 | D18: DOB below 18 years is rejected | E18: R-CLI-01 | F18: SDC-04 | G18: UI | H18: Boundary | I18: P1 | J18: highest linked risk R-CLI-01 (score 9) | K18: @regression @client @SDC-04 | L18: New application on the client step. | M18: DOB = today - 18y + 1 day (age 17y 364d) | N18: 1. Enter the underage DOB. 2. Move focus away from the field. 3. Try to continue. | O18: - Per Functional Modules 3.3 an eligibility error appears at entry; expected text "Client age must be between 18 and 65 years.". - If the app only raises it on review/validate, record WHERE it appears and log it as an observation for SDC-04. | P18: client-dob-input; message "Client age must be between 18 and 65 years." (validation summary) | Q18: ClientInformationPage | R18: Screenshot of eligibility error with DOB visible. | S18: OI-15 | T18: D, S | U18: Needs confirmation | V18: Not run
A19: TC-CLI-004 | B19: Client / insured information | C19: CLI-V04 | D19: DOB above 65 years is rejected | E19: R-CLI-01 | F19: SDC-04 | G19: UI | H19: Boundary | I19: P1 | J19: highest linked risk R-CLI-01 (score 9) | K19: @regression @client @SDC-04 | L19: New application on the client step. | M19: DOB = today - 66y | N19: 1. Enter the DOB. 2. Move focus away. 3. Try to continue. | O19: - Eligibility error "Client age must be between 18 and 65 years." appears at entry (or at the latest in the validation summary: record where). | P19: client-dob-input; message "Client age must be between 18 and 65 years." | Q19: ClientInformationPage | R19: Screenshot of eligibility error. | S19: OI-15 | T19: D, S | U19: Needs confirmation | V19: Not run
A20: TC-CLI-005 | B20: Client / insured information | C20: CLI-V05 | D20: Future date of birth is rejected | E20: R-CLI-02 | F20: SDC-05 | G20: UI | H20: Negative | I20: P2 | J20: highest linked risk R-CLI-02 (score 6) | K20: @regression @client @SDC-05 | L20: New application on the client step. | M20: DOB = today + 1 day; DOB = today + 10y | N20: 1. Enter tomorrow as DOB. 2. Observe validation. 3. Repeat with today + 10 years. 4. Reload and confirm nothing was saved. | O20: - Error "Future date of birth is not allowed." appears for both values. - Nothing is saved (reload shows no future DOB; API GET client shows none). | P20: client-dob-input; message "Future date of birth is not allowed." | Q20: ClientInformationPage | R20: Screenshot of error. | T20: D, S | U20: Ready | V20: Not run
A21: TC-CLI-006 | B21: Client / insured information | C21: CLI-P01 | D21: Age boundary values 18 and 65 are accepted | E21: R-CLI-01 | F21: SDC-04 | G21: UI | H21: Boundary | I21: P1 | J21: highest linked risk R-CLI-01 (score 9) | K21: @regression @client @SDC-04 | L21: New application on the client step. PROPOSED test (not in source). | M21: DOB = today - 18y; DOB = today - 65y | N21: 1. Enter DOB for exactly 18 years. 2. Observe validation and continue. 3. Repeat with exactly 65 years. | O21: - Both DOBs are accepted: the rule is inclusive (error only when age < 18 or > 65). - review-client-calculated-age shows 18 and 65 respectively. | P21: client-dob-input; review-client-calculated-age | Q21: ClientInformationPage | R21: Screenshot for both values. | T21: S | U21: Ready | V21: Not run
A22: TC-CLI-007 | B22: Client / insured information | C22: CLI-P02 | D22: Age is calculated correctly from the date of birth | E22: R-CLI-04 | G22: UI | H22: Boundary | I22: P3 | J22: highest linked risk R-CLI-04 (score 4) | K22: @regression @client | L22: Complete application up to the review page, or read calculated_age through GET /api/applications/{id}. | M22: Birthday today (age n); birthday tomorrow (age n-1); 29 February DOB | N22: 1. Enter each DOB. 2. Read the displayed age. 3. Compare with age computed in the test from system date. | O22: - Displayed/stored age equals the age computed by the test from the system date for each DOB. | P22: review-client-calculated-age (age is displayed on the review page) | Q22: ClientInformationPage | R22: Screenshot per DOB. | T22: S | U22: Ready | V22: Not run
A23: TC-CLI-008 | B23: Client / insured information | C23: CLI-P03 | D23: Name and personal field format validation | E23: R-CLI-03 | G23: UI | H23: Negative | I23: P3 | J23: highest linked risk R-CLI-03 (score 4) | K23: @regression @client | L23: New application on the client step. PROPOSED test. | M23: Names: "12345", "@@@", 101-character string, whitespace only; valid: "Anne-Marie O'Neil" | N23: 1. Enter each invalid value in first and last name. 2. Observe errors. 3. Enter the valid value. | O23: - Invalid values are rejected with an inline error. - The valid hyphenated/apostrophe name is accepted. | P23: client-first-name-input, client-middle-name-input, client-last-name-input, client-dob-input, client-gender-select, client-marital-status-select, client-nationality-input, client-occupation-input, client-employer-name-input, client-employer-address-input, client-save-continue-button | Q23: ClientInformationPage | R23: Screenshot per value. | T23: D, V | U23: Ready | V23: Not run
A24: TC-ADR-001 | B24: Address & contact | C24: CLI-V06 | D24: Same-as-residential copies data to mailing address | E24: R-ADR-01 | G24: UI | H24: Functional | I24: P3 | J24: highest linked risk R-ADR-01 (score 4) | K24: @regression @address | L24: Application on the address and contact step. | M24: Residential: 10 Main St, New York, NY, 10001 | N24: 1. Fill residential address. 2. Tick "same as residential". 3. Compare mailing fields. 4. Edit a residential field. 5. Untick the checkbox. | O24: - Mailing fields equal residential after ticking. - Edit residential then save: mailing behaviour matches what is shown (record whether it follows). - Unticking makes mailing editable. | P24: residential-address-line-1/2-input, residential-city-input, residential-state-province-select, residential-postal-code-input, address-same-as-residential-checkbox, mailing-* (same ids), contact-primary-email-input, contact-mobile-number-input, contact-alternate-phone-input, contact-preferred-mode-select, address-contact-save-continue-button | Q24: AddressContactPage | R24: Screenshot after tick and after edit. | T24: S | U24: Ready | V24: Not run
A25: TC-ADR-002 | B25: Address & contact | C25: CLI-V07a | D25: Invalid email formats are rejected | E25: R-ADR-02 | G25: UI | H25: Negative | I25: P3 | J25: highest linked risk R-ADR-02 (score 4) | K25: @regression @address | L25: Application on the address and contact step. | M25: TD-EMAIL: "abc", "a@b", "a@@b.com", "a b@c.com"; valid "qa.user@example.com" | N25: 1. Enter each invalid email. 2. Observe validation. 3. Enter the valid email. | O25: - Each invalid email shows an error and blocks progression. - Valid email is accepted. | P25: contact-primary-email-input | Q25: AddressContactPage | R25: Screenshot per invalid value. | T25: S | U25: Ready | V25: Not run
A26: TC-ADR-003 | B26: Address & contact | C26: CLI-V07b | D26: Invalid phone formats are rejected | E26: R-ADR-02 | G26: UI | H26: Negative | I26: P3 | J26: highest linked risk R-ADR-02 (score 4) | K26: @regression @address | L26: Application on the address and contact step. | M26: US phone rule: optional +1, area code and exchange start 2-9, 10 digits. Invalid: 123 | (055) 123-4567 | +44 20 7946 0958 | 555-0100. Valid: (212) 555-0147 | +1 212-555-0147 | 2125550147 | N26: 1. Enter each invalid value in mobile and alternate phone. 2. Observe validation. 3. Enter a valid number. | O26: - Each invalid value shows an error. - Valid number is accepted. | P26: contact-mobile-number-input, contact-alternate-phone-input | Q26: AddressContactPage | R26: Screenshot per invalid value. | T26: S | U26: Ready | V26: Not run
A27: TC-ADR-004 | B27: Address & contact | C27: ADR-P01 | D27: Postal code format is validated | E27: R-ADR-02 | G27: UI | H27: Negative | I27: P3 | J27: highest linked risk R-ADR-02 (score 4) | K27: @regression @address | L27: Address step. PROPOSED test. | M27: US ZIP rule: 5 digits or ZIP+4. Invalid: 1234 | 123456 | ABCDE | 12345-12. Valid: 10001 | 10001-1234. State must be a US state/DC code. | N27: 1. Enter each invalid postal code. 2. Observe validation. 3. Enter a valid one. | O27: - Invalid codes are rejected; valid code accepted. | P27: residential-postal-code-input, mailing-postal-code-input, *-state-province-select | Q27: AddressContactPage | R27: Screenshot per value. | T27: S | U27: Ready | V27: Not run
A28: TC-ADR-005 | B28: Address & contact | C28: ADR-P02 | D28: Mailing address is mandatory when not same as residential | E28: R-ADR-03 | G28: UI | H28: Negative | I28: P3 | J28: highest linked risk R-ADR-03 (score 2) | K28: @regression @address | L28: Address step. PROPOSED test. | M28: Valid residential; mailing blank | N28: 1. Fill residential. 2. Leave "same as residential" unticked. 3. Leave mailing blank and try to continue. | O28: - Required mailing fields show errors and progression is blocked. | P28: mailing-* inputs; message "Residential and mailing addresses are required." (validation summary) | Q28: AddressContactPage | R28: Screenshot of errors. | T28: D, S | U28: Ready | V28: Not run
A29: TC-ADR-006 | B29: Address & contact | C29: ADR-P03 | D29: Preferred communication mode is required | E29: R-ADR-03 | G29: UI | H29: Negative | I29: P3 | J29: highest linked risk R-ADR-03 (score 2) | K29: @regression @address | L29: Address step. PROPOSED test. | M29: Options: EMAIL, PHONE, MAIL (Postal Mail) | N29: 1. Fill all contact data but leave preferred mode unselected. 2. Try to continue. 3. Select each available mode in turn. | O29: - Error appears and progression is blocked while unselected. - Each mode, once selected, is accepted. | P29: contact-preferred-mode-select | Q29: AddressContactPage | R29: Screenshot of error. | T29: S | U29: Ready | V29: Not run
A30: TC-KYC-001 | B30: KYC, financial & compliance | C30: CLI-V08 | D30: SSN is masked after entry (all screens and responses) | E30: R-KYC-01 | F30: SDC-07 | G30: UI + API | H30: Negative | I30: P1 | J30: highest linked risk R-KYC-01 (score 9) | K30: @regression @api @kyc @SDC-07 | L30: Application on the KYC step. | M30: ID type SSN; value 123-45-6789 (fake) | N30: 1. Enter the SSN and leave the field. 2. Read the displayed value. 3. Continue, then return to the field. 4. Open the review page and confirmation (if reachable). 5. Inspect network responses carrying the client/KYC data for the full SSN string. | O30: - After save only the last four digits are readable: pattern ******* + 6789 (all characters but the last 4 replaced by *, whitespace removed). - Full SSN is not in page text, screenshots, or API responses (only id_number_masked and a hash are returned). - Q-18 was not answered: this pattern is derived from the app and must be confirmed in the UI. | P30: kyc-id-type-select, kyc-id-number-input, kyc-issue-date-input, kyc-expiry-date-input, financial-annual-income-input, financial-net-worth-input, financial-source-of-funds-select, financial-risk-profile-select, compliance-pep-select, compliance-pep-details-input, compliance-declaration-checkbox, kyc-financial-save-continue-button; masked value also on review page; API GET /api/applications/{id} | Q30: KycFinancialPage, ReviewPage, apiClient | R30: Screenshots of each screen; network response excerpt with SSN redacted. | S30: OI-13 | T30: S, V | U30: Needs confirmation | V30: Not run
A31: TC-KYC-002 | B31: KYC, financial & compliance | C31: CLI-V09 | D31: KYC upload rejects unsupported file type | E31: R-DOC-01 | G31: UI | H31: Negative | I31: P3 | J31: highest linked risk R-DOC-01 (score 4) | K31: @regression @kyc | L31: Documents page. In this build the KYC upload control is on /documents, not on the KYC form. | M31: invalid.exe, invalid.txt (generated); document type KYC_ID | N31: 1. Upload invalid.exe. 2. Upload invalid.txt. 3. Check the document list. | O31: - Message "Unsupported document format. Accepted formats are PDF, JPG, and PNG." is shown for each. - No row appears in documents-table. | P31: /applications/{id}/documents: document-type-select = KYC_ID, document-upload-kyc (file), document-upload-button | Q31: KycFinancialPage, fileUploadHelper | R31: Screenshot of error. | T31: S, M | U31: Ready | V31: Not run
A32: TC-KYC-003 | B32: KYC, financial & compliance | C32: CLI-V10 | D32: PEP = Yes requires additional details | E32: R-KYC-05 | G32: UI | H32: Functional | I32: P2 | J32: highest linked risk R-KYC-05 (score 6) | K32: @regression @kyc | L32: Application on the compliance section. | M32: PEP = Yes with and without details | N32: 1. Select PEP = No and observe. 2. Select PEP = Yes. 3. Leave details blank and try to continue. 4. Enter details and continue. | O32: - Details field is hidden for No and shown for Yes. - Blank details block progression with an error. - Valid details are accepted. | P32: compliance-pep-select (0/1), compliance-pep-details-input | Q32: KycFinancialPage | R32: Screenshot of details field and error. | T32: D, S | U32: Ready | V32: Not run
A33: TC-KYC-004 | B33: KYC, financial & compliance | C33: KYC-P01 | D33: Income versus premium affordability is validated | E33: R-KYC-03 | F33: SDC-08 | G33: UI + API | H33: Negative | I33: P1 | J33: highest linked risk R-KYC-03 (score 9) | K33: @regression @api @kyc @SDC-08 | L33: Client step done. PROPOSED test. | M33: SecureLife (WL_SECURE_BASIC), face 250,000, monthly: annual premium 1,187.50. Income 5,000 (limit 1,000 = 20%) must fail; income 50,000 (limit 10,000) must pass. See Test_Data premium calculator. | N33: 1. Enter a low annual income on the KYC step. 2. Configure a product with a high premium. 3. Run validation / proceed to review. 4. Repeat with adequate income. | O33: - Low-income case: "Premium exceeds affordability threshold." appears on validate/review. - Adequate income: no affordability message. - POST /api/applications/{id}/validate returns the same finding. - Confirm in the UI that the rule compares ANNUAL premium with 20% of annual income. | P33: kyc-id-type-select, kyc-id-number-input, kyc-issue-date-input, kyc-expiry-date-input, financial-annual-income-input, financial-net-worth-input, financial-source-of-funds-select, financial-risk-profile-select, compliance-pep-select, compliance-pep-details-input, compliance-declaration-checkbox, kyc-financial-save-continue-button; message "Premium exceeds affordability threshold." (review/validate) | Q33: KycFinancialPage, ProductConfigurationPage, apiClient | R33: Screenshot of warning; validate API response. | S33: OI-11 | T33: S | U33: Needs confirmation | V33: Not run
A34: TC-KYC-005 | B34: KYC, financial & compliance | C34: KYC-P02 | D34: ID number validation changes with ID type | E34: R-KYC-04 | G34: UI | H34: Negative | I34: P3 | J34: highest linked risk R-KYC-04 (score 4) | K34: @regression @kyc | L34: KYC step. PROPOSED test. | M34: TD-ID: for each ID type, one invalid and one valid sample [V] | N34: 1. Select an ID type. 2. Enter an invalid ID number and observe. 3. Enter a valid number. 4. Switch ID type and observe that rules change. | O34: - Invalid numbers are rejected per type; valid ones accepted. - Changing type re-validates the entered number. | P34: kyc-id-type-select options: SSN, STATE_ID, PASSPORT, DRIVERS_LICENSE; kyc-id-number-input | Q34: KycFinancialPage | R34: Screenshot per ID type. | T34: S | U34: Ready | V34: Not run
A35: TC-KYC-006 | B35: KYC, financial & compliance | C35: KYC-P03 | D35: Incomplete compliance declaration blocks progression | E35: R-KYC-05 | G35: UI + API | H35: Negative | I35: P2 | J35: highest linked risk R-KYC-05 (score 6) | K35: @regression @api @kyc | L35: KYC step. PROPOSED test. | M35: Compliance declaration left unanswered | N35: 1. Complete KYC and financial data but leave the compliance declaration incomplete. 2. Try to continue. 3. Call POST .../validate. 4. Complete the declaration. | O35: - Progression is blocked with an error. - Validate API reports the missing declaration. - After completion progression is allowed. | P35: compliance-declaration-checkbox; message "Compliance declarations must be completed." | Q35: KycFinancialPage, apiClient | R35: Screenshot; validate API response. | T35: S | U35: Ready | V35: Not run
A36: TC-PROD-001 | B36: Product selection & policy config | C36: PROD-V01 | D36: Product catalog displays the expected Whole Life products | E36: R-PROD-05 | G36: UI + API | H36: Smoke | I36: P1 | J36: Smoke test; highest linked risk R-PROD-05 (score 4) | K36: @smoke @regression @api @product | L36: Logged in; client steps completed or /products reachable. | M36: 5 active products: WL_SECURE_BASIC, WL_WEALTH_BUILDER, WL_ELITE_LEGACY, WL_FLEXI_PAY, WL_GUARANTEED_RETURN | N36: 1. Open /products. 2. Count and read product cards and names. 3. Call GET /api/products. 4. Compare. | O36: - 5 product cards, one per code above (UI order: by product name). - Names and codes equal /api/products. | P36: /products: product-card-{code}, product-details-{code}; GET /api/products | Q36: ProductCatalogPage, apiClient | R36: Screenshot of catalog; list of names compared. | T36: S | U36: Ready | V36: Not run
A37: TC-PROD-002 | B37: Product selection & policy config | C37: PROD-V02 | D37: Product details page opens correctly | E37: R-PROD-05; R-PROD-06 | G37: UI | H37: Functional | I37: P3 | J37: highest linked risk R-PROD-06 (score 4) | K37: @regression @product | L37: Catalog visible. | M37: Coverage term options WHOLE_LIFE and TO_AGE_100; payment term in years (1-100) | N37: 1. Click a product. 2. Check URL /products/:productId. 3. Read features, eligibility, coverage limits and benefits. 4. Open payment-term and policy-term options on the configuration step. | O37: - Details page opens with features, eligibility, coverage limits and benefits visible. - Payment and policy term options match the product rules (values from Test Data Guide). | P37: product-detail-page, product-name, product-code, product-features; product-payment-term-select, product-coverage-term-select | Q37: ProductCatalogPage, ProductConfigurationPage | R37: Screenshot of details page. | T37: S | U37: Ready | V37: Not run
A38: TC-PROD-003 | B38: Product selection & policy config | C38: PROD-V03 | D38: Face value below minimum is rejected | E38: R-PROD-02 | G38: UI + API | H38: Boundary | I38: P2 | J38: highest linked risk R-PROD-02 (score 6) | K38: @regression @api @product | L38: Product selected; configuration step. | M38: Face value limits (min/max): SecureLife 100,000/1,000,000; WealthBuilder 150,000/1,500,000; Elite Legacy 500,000/5,000,000; FlexiPay 100,000/1,200,000; Guaranteed Return 200,000/2,000,000. Use SecureLife: 99,999 (reject) and 100,000 (accept); repeat for each product. | N38: 1. Enter face value = minimum - 1. 2. Observe validation. 3. Enter face value = minimum. 4. Repeat through the API if an endpoint exists. | O38: - Below-minimum value shows an error and blocks progression. - Minimum value is accepted. | P38: product-sum-assured-input, product-range-help | Q38: ProductConfigurationPage, apiClient | R38: Screenshot of error. | T38: S | U38: Ready | V38: Not run
A39: TC-PROD-004 | B39: Product selection & policy config | C39: PROD-V04 | D39: Face value above maximum is rejected | E39: R-PROD-02 | G39: UI + API | H39: Boundary | I39: P2 | J39: highest linked risk R-PROD-02 (score 6) | K39: @regression @api @product | L39: Product selected; configuration step. | M39: Face value limits (min/max): SecureLife 100,000/1,000,000; WealthBuilder 150,000/1,500,000; Elite Legacy 500,000/5,000,000; FlexiPay 100,000/1,200,000; Guaranteed Return 200,000/2,000,000. Use SecureLife: 1,000,001 (reject) and 1,000,000 (accept); repeat for each product. | N39: 1. Enter face value = maximum + 1. 2. Observe validation. 3. Enter face value = maximum. | O39: - Above-maximum value shows an error and blocks progression. - Maximum value is accepted. | P39: product-sum-assured-input, product-range-help | Q39: ProductConfigurationPage, apiClient | R39: Screenshot of error. | T39: S | U39: Ready | V39: Not run
A40: TC-PROD-005 | B40: Product selection & policy config | C40: PROD-V05 | D40: Premium recalculates when premium frequency changes | E40: R-PROD-03 | F40: SDC-12 | G40: UI + API | H40: Reconciliation | I40: P1 | J40: highest linked risk R-PROD-03 (score 9) | K40: @regression @api @product @SDC-12 | L40: Product selected with a valid face value. | M40: Formula: annual = face/1000 x product rate; period premium = annual / 12, 4, 2 or 1, rounded to 2 decimals. SecureLife (4.75), face 250,000: 98.96 monthly, 296.88 quarterly, 593.75 semi-annual, 1,187.50 annual (tolerance 0.01). See Test_Data calculator. | N40: 1. Set a face value. 2. Select each frequency in turn and read the premium. 3. Change the face value and read again. 4. Compare each UI premium with the API value for the application. | O40: - Premium changes with each frequency and face value as per the formula. - UI value equals the expected value and the API/total premium after save. | P40: product-premium-frequency-select (MONTHLY, QUARTERLY, SEMI_ANNUAL, ANNUAL), product-current-total-premium, premium-preview-help | Q40: ProductConfigurationPage, apiClient | R40: Table of inputs / UI premium / API premium. | T40: S | U40: Ready | V40: Not run
A41: TC-PROD-006 | B41: Product selection & policy config | C41: PROD-V06 | D41: Premium on review page matches configuration page | E41: R-PROD-04 | F41: SDC-12 | G41: UI + API | H41: Reconciliation | I41: P2 | J41: highest linked risk R-PROD-04 (score 6) | K41: @regression @api @product @SDC-12 | L41: Application configured through the product step. | M41: Face value F, frequency Monthly, optional ADB rider | N41: 1. Capture premium on the configuration page. 2. Navigate to the review page. 3. Capture the premium shown. 4. Return, change face value, review again. | O41: - Review premium equals configuration premium after each change. - Matches API premium. | P41: product-current-total-premium, review-total-premium, application-total-premium | Q41: ProductConfigurationPage, ReviewPage | R41: Both premium values attached. | T41: S | U41: Ready | V41: Not run
A42: TC-PROD-007 | B42: Product selection & policy config | C42: PROD-V07 | D42: Product suitability warning appears on mismatch | E42: R-PROD-01 | F42: SDC-09 | G42: UI + API | H42: Negative | I42: P1 | J42: highest linked risk R-PROD-01 (score 9) | K42: @regression @api @product @SDC-09 | L42: Client risk profile and age set to an unsuitable combination (per Test Data Guide). | M42: Client age 19 with WealthBuilder (min 21); client age 63 with Guaranteed Return (max 55) / FlexiPay (max 62); risk-profile mismatch text to be captured [V] | N42: 1. Set the unsuitable profile on the KYC step. 2. Select the product. 3. Observe warning. 4. Call POST .../validate. 5. Repeat with a suitable profile. | O42: - A suitability / eligibility warning or error is shown for age outside the product range. - POST /api/applications/{id}/validate reports the same. - An in-range client shows no such message. - Capture the exact warning text; the risk-profile suitability rule is not stated in the docs. | P42: Product eligibility ages (min-max): SecureLife 18-65; WealthBuilder 21-60; Elite 30-65; FlexiPay 18-62; Guaranteed Return 25-55 | Q42: KycFinancialPage, ProductConfigurationPage, apiClient | R42: Screenshot of warning; validate response. | S42: OI-11 | T42: S, V | U42: Needs confirmation | V42: Not run
A43: TC-RID-001 | B43: Rider selection | C43: RIDER-V01 | D43: Agent can add an eligible protection rider (ADB) | E43: R-RID-05 | G43: UI | H43: Functional | I43: P2 | J43: highest linked risk R-RID-05 (score 6) | K43: @regression @rider | L43: Policy configured; client eligible. | M43: RIDER_ADB (Accidental Death Benefit, protection) with coverage = face value 250,000: rate 0.85 per 1,000 = 212.50/year (17.71 monthly) | N43: 1. Open the riders step. 2. Select ADB. 3. Enter valid coverage. 4. Open the premium summary. | O43: - Rider appears in the premium summary. - Total premium increases by the itemised rider premium. | P43: riders-page, rider-selected-{id}, rider-coverage-amount-{id}, rider-row-{id}, rider-premium-summary, rider-save-continue-button; GET /api/riders | Q43: RiderSelectionPage | R43: Screenshot of summary. | T43: S | U43: Ready | V43: Not run
A44: TC-RID-002 | B44: Rider selection | C44: RIDER-V02 | D44: Rider coverage cannot exceed base policy face value | E44: R-RID-01 | F44: SDC-10 | G44: UI + API | H44: Boundary | I44: P1 | J44: highest linked risk R-RID-01 (score 9) | K44: @regression @api @rider @SDC-10 | L44: Policy face value F configured. | M44: Face value F; rider coverage F + 1 must be rejected, F accepted. Capped riders: Critical Illness max 500,000; Hospital Cash 100,000 (fixed); Family Income 750,000; Guaranteed Income 500,000 | N44: 1. Select a rider. 2. Enter coverage F + 1. 3. Observe validation. 4. Enter coverage F. 5. Attempt the same through the API. | O44: - Coverage above F is rejected with an error and progression blocked. - Coverage equal to F is accepted (if rule is <=). - API rejects the above-limit request. | P44: riders-page, rider-selected-{id}, rider-coverage-amount-{id}, rider-row-{id}, rider-premium-summary, rider-save-continue-button; GET /api/riders | Q44: RiderSelectionPage, apiClient | R44: Screenshot of error; API response. | T44: S | U44: Ready | V44: Not run
A45: TC-RID-003 | B45: Rider selection | C45: RIDER-V03 | D45: Age-ineligible rider cannot be added | E45: R-RID-03 | G45: UI + API | H45: Negative | I45: P2 | J45: highest linked risk R-RID-03 (score 6) | K45: @regression @api @rider | L45: Client age outside the rider age range. | M45: Max riders per application: 4. Rider age ranges: ADB 18-65; Disability 18-60; Term Add-on 21-55; Critical Illness 18-58; Hospital Cash 18-60; Waiver Disability 18-55; Waiver CI 18-55; Family Income 25-55; Guaranteed Income 30-60. Use client age 62: Disability, Term Add-on, Critical Illness, Hospital Cash must be ineligible; ADB eligible. | N45: 1. Open riders step for an ineligible client. 2. Try to select the rider. 3. Attempt via API. | O45: - Rider is disabled or an eligibility error is displayed. - API rejects the add. | P45: riders-page, rider-selected-{id}, rider-coverage-amount-{id}, rider-row-{id}, rider-premium-summary, rider-save-continue-button; GET /api/riders | Q45: RiderSelectionPage, apiClient | R45: Screenshot of disabled state. | T45: S | U45: Ready | V45: Not run
A46: TC-RID-004 | B46: Rider selection | C46: RIDER-V04 | D46: Maximum rider count is enforced | E46: R-RID-04 | G46: UI | H46: Boundary | I46: P3 | J46: highest linked risk R-RID-04 (score 4) | K46: @regression @rider | L46: Eligible client; several eligible riders available. | M46: Max riders per application: 4. Rider age ranges: ADB 18-65; Disability 18-60; Term Add-on 21-55; Critical Illness 18-58; Hospital Cash 18-60; Waiver Disability 18-55; Waiver CI 18-55; Family Income 25-55; Guaranteed Income 30-60. Face value 500,000, client age 40: select 4 eligible riders (accepted), then a 5th (blocked). | N46: 1. Add riders one by one up to N. 2. Try to add rider N + 1. | O46: - Rider N + 1 is blocked with a message. - Existing N riders remain unchanged. | P46: riders-page, rider-selected-{id}, rider-coverage-amount-{id}, rider-row-{id}, rider-premium-summary, rider-save-continue-button; GET /api/riders | Q46: RiderSelectionPage | R46: Screenshot of blocking message. | T46: S | U46: Ready | V46: Not run
A47: TC-RID-005 | B47: Rider selection | C47: RIDER-V05 | D47: Mutually exclusive waiver riders cannot both be selected | E47: R-RID-02 | F47: SDC-11 | G47: UI + API | H47: Negative | I47: P2 | J47: highest linked risk R-RID-02 (score 6) | K47: @regression @api @rider @SDC-11 | L47: Both waiver riders available for the client. | M47: Mutually exclusive group WAIVER_PREMIUM: RIDER_WAIVER_DISABILITY and RIDER_WAIVER_CI (both need base face value >= 200,000). | N47: 1. Select waiver A. 2. Try to select waiver B. 3. Deselect A and select B. 4. Attempt both together through the API. | O47: - Waiver B is disabled or blocked while A is selected. - After deselecting A, B can be selected. - API rejects both together. | P47: riders-page, rider-selected-{id}, rider-coverage-amount-{id}, rider-row-{id}, rider-premium-summary, rider-save-continue-button; GET /api/riders | Q47: RiderSelectionPage, apiClient | R47: Screenshot of blocked state. | T47: S | U47: Ready | V47: Not run
A48: TC-RID-006 | B48: Rider selection | C48: RIDER-V06 | D48: Critical illness rider triggers the health questionnaire | E48: R-RID-06 | G48: UI | H48: Functional | I48: P3 | J48: highest linked risk R-RID-06 (score 4) | K48: @regression @rider | L48: Riders step. | M48: Riders flagged health questionnaire: RIDER_CRITICAL_ILLNESS, RIDER_WAIVER_CI | N48: 1. Select the CI rider. 2. Observe the page. 3. Try to continue with the questionnaire blank. 4. Deselect the rider. | O48: - Per Functional Modules 3.5 a health questionnaire section appears for these riders. If the UI shows none, record it as an observation (candidate defect) rather than failing silently. | P48: riders-page, rider-selected-{id}, rider-coverage-amount-{id}, rider-row-{id}, rider-premium-summary, rider-save-continue-button; GET /api/riders (no questionnaire test id in markup: capture selector at first run) | Q48: RiderSelectionPage | R48: Screenshot of questionnaire. | S48: OI-15 | T48: D, V | U48: Needs confirmation | V48: Not run
A49: TC-RID-007 | B49: Rider selection | C49: RIDER-V07 | D49: Rider premium is itemized in total premium | E49: R-RID-05 | F49: SDC-12 | G49: UI + API | H49: Reconciliation | I49: P2 | J49: highest linked risk R-RID-05 (score 6) | K49: @regression @api @rider @SDC-12 | L49: Base policy configured. | M49: Rider premium = coverage/1000 x rider rate (ADB 0.85, Disability 1.10, Term 1.25, CI 1.60, Hospital 0.65, Waiver Dis 0.70, Waiver CI 0.90, Family 1.35, Guaranteed 1.50) | N49: 1. Note base premium. 2. Add a rider and read itemised premium and total. 3. Remove the rider. 4. Compare with API. | O49: - Total = base + sum of itemised rider premiums. - Removing a rider restores the previous total. - UI equals API. | P49: rider-premium-summary, product-current-total-premium | Q49: RiderSelectionPage, apiClient | R49: Premium table attached. | T49: S | U49: Ready | V49: Not run
A50: TC-BEN-001 | B50: Beneficiary management | C50: BEN-V01 | D50: Add a valid primary beneficiary (and irrevocable confirmation) | E50: R-BEN-04; R-BEN-06 | G50: UI | H50: Smoke | I50: P1 | J50: Smoke test; highest linked risk R-BEN-06 (score 6) | K50: @smoke @regression @beneficiary | L50: Beneficiaries step. | M50: Individual adult beneficiary, relationship Spouse, allocation 100% | N50: 1. Open the beneficiaries step. 2. Fill the form and save. 3. Observe the list and running total. 4. Extension: mark the beneficiary Irrevocable and observe the modal; cancel then accept. | O50: - Beneficiary card/row appears with entered values. - Primary running total shows 100%. - Irrevocable selection opens the legal confirmation modal; Cancel leaves it unchecked; Accept applies it. | P50: beneficiary-level-select (PRIMARY/SECONDARY), beneficiary-type-select (INDIVIDUAL/TRUST/ORGANIZATION), beneficiary-relationship-select (SPOUSE, CHILD, PARENT, SIBLING, TRUST, ORGANIZATION, OTHER), beneficiary-first-name/last-name/dob/allocation-input, beneficiary-designation-select (0 revocable / 1 irrevocable), beneficiary-legal-acknowledgement-checkbox, beneficiary-allocation-summary, beneficiary-error-summary, beneficiary-row-{id}, beneficiary-edit-{id}, beneficiary-delete-{id}, beneficiary-continue-button | Q50: BeneficiaryPage | R50: Screenshot of list and modal. | T50: S | U50: Ready | V50: Not run
A51: TC-BEN-002 | B51: Beneficiary management | C51: BEN-V02 | D51: Primary allocation below 100% blocks progression | E51: R-BEN-01 | F51: SDC-13 | G51: UI | H51: Boundary | I51: P1 | J51: highest linked risk R-BEN-01 (score 9) | K51: @regression @beneficiary @SDC-13 | L51: Beneficiaries step. | M51: Primary 60% + 30% = 90% | N51: 1. Add two primary beneficiaries totalling 90%. 2. Observe errors. 3. Try to continue. 4. Adjust to 100%. | O51: - Allocation error is shown and progression is blocked. - At 100% the error clears. | P51: beneficiary-allocation-summary, beneficiary-error-summary, beneficiary-allocation-input | Q51: BeneficiaryPage | R51: Screenshot of error and running total. | T51: D, S | U51: Ready | V51: Not run
A52: TC-BEN-003 | B52: Beneficiary management | C52: BEN-V03 | D52: Primary allocation above 100% blocks progression | E52: R-BEN-01 | F52: SDC-13 | G52: UI | H52: Boundary | I52: P1 | J52: highest linked risk R-BEN-01 (score 9) | K52: @regression @beneficiary @SDC-13 | L52: Beneficiaries step. | M52: Primary 60% + 50% = 110% | N52: 1. Add two primary beneficiaries totalling 110%. 2. Observe errors. 3. Try to continue. | O52: - Over-allocation error is shown and progression is blocked. | P52: beneficiary-allocation-summary, beneficiary-error-summary, beneficiary-allocation-input | Q52: BeneficiaryPage | R52: Screenshot of error. | T52: D, S | U52: Ready | V52: Not run
A53: TC-BEN-004 | B53: Beneficiary management | C53: BEN-V04 | D53: Secondary allocation is validated separately | E53: R-BEN-01 | F53: SDC-13 | G53: UI | H53: Boundary | I53: P1 | J53: highest linked risk R-BEN-01 (score 9) | K53: @regression @beneficiary @SDC-13 | L53: Beneficiaries step with primary at 100%. | M53: Secondary 50% + 30% = 80%, then 100% | N53: 1. Add a valid primary set totalling 100%. 2. Add secondary beneficiaries totalling 80%. 3. Observe errors. 4. Adjust secondary to 100%. | O53: - Secondary group shows its own error while primary shows none. - At 100% secondary the error clears. | P53: beneficiary-allocation-summary, beneficiary-error-summary, beneficiary-allocation-input | Q53: BeneficiaryPage | R53: Screenshot of separate totals. | T53: D, S | U53: Ready | V53: Not run
A54: TC-BEN-005 | B54: Beneficiary management | C54: BEN-V05 | D54: Minor beneficiary requires guardian details | E54: R-BEN-02 | F54: SDC-14 | G54: UI | H54: Negative | I54: P1 | J54: highest linked risk R-BEN-02 (score 9) | K54: @regression @beneficiary @SDC-14 | L54: Beneficiaries step. | M54: Beneficiary DOB = today - 17y; then adult DOB | N54: 1. Enter a beneficiary with a minor DOB. 2. Observe guardian fields. 3. Leave guardian blank and save. 4. Fill guardian details and save. 5. Change DOB to adult. | O54: - Guardian fields appear and are mandatory for the minor. - Saving without guardian is blocked. - Guardian fields hide for an adult. | P54: minor-guardian-section, beneficiary-guardian-name-input, beneficiary-guardian-relationship-input, beneficiary-guardian-contact-input, beneficiary-guardian-address-input | Q54: BeneficiaryPage | R54: Screenshot of guardian error. | T54: S | U54: Ready | V54: Not run
A55: TC-BEN-006 | B55: Beneficiary management | C55: BEN-V06 | D55: Trust beneficiary shows trust-specific fields | E55: R-BEN-05 | G55: UI | H55: Functional | I55: P3 | J55: highest linked risk R-BEN-05 (score 4) | K55: @regression @beneficiary | L55: Beneficiaries step. | M55: Type = Trust | N55: 1. Select Trust as beneficiary type. 2. Observe the form. 3. Leave trust fields blank and save. | O55: - Trust Name, Trustee Name and Trust Date fields appear. - Individual-only fields are hidden. - Blank trust fields block saving. | P55: beneficiary-trust-name-input, beneficiary-trust-date-input, beneficiary-trustee-name-input, beneficiary-trustee-contact-input | Q55: BeneficiaryPage | R55: Screenshot of trust fields. | T55: S | U55: Ready | V55: Not run
A56: TC-BEN-007 | B56: Beneficiary management | C56: BEN-V07 | D56: Organization beneficiary shows organization-specific fields | E56: R-BEN-05 | G56: UI | H56: Functional | I56: P3 | J56: highest linked risk R-BEN-05 (score 4) | K56: @regression @beneficiary | L56: Beneficiaries step. | M56: Type = Organization | N56: 1. Select Organization. 2. Observe the form. 3. Leave fields blank and save. | O56: - Registration and contact fields appear. - Blank mandatory fields block saving. | P56: beneficiary-organization-name-input, beneficiary-organization-registration-input, beneficiary-organization-contact-input | Q56: BeneficiaryPage | R56: Screenshot of organization fields. | T56: S | U56: Ready | V56: Not run
A57: TC-BEN-008 | B57: Beneficiary management | C57: BEN-V08 | D57: Duplicate beneficiary is blocked | E57: R-BEN-03 | F57: SDC-15 | G57: UI + API | H57: Negative | I57: P2 | J57: highest linked risk R-BEN-03 (score 6) | K57: @regression @api @beneficiary @SDC-15 | L57: One beneficiary already added. | M57: Same Name + DOB + Relationship; variant with different relationship | N57: 1. Add the same Name, DOB and Relationship again. 2. Observe error. 3. Add a variant with a different relationship. 4. Read the list via GET .../beneficiaries. | O57: - Duplicate is blocked with an error. - Only one row exists (UI and API). - The different-relationship variant is allowed. | P57: beneficiary-error-summary, beneficiary-row-{id}; GET /api/applications/{id}/beneficiaries | Q57: BeneficiaryPage, apiClient | R57: Screenshot of error; API list. | T57: D, S | U57: Ready | V57: Not run
A58: TC-BEN-009 | B58: Beneficiary management | C58: BEN-V09 | D58: Removing a beneficiary updates the allocation total | E58: R-BEN-04 | G58: UI | H58: Functional | I58: P3 | J58: highest linked risk R-BEN-04 (score 4) | K58: @regression @beneficiary | L58: Three primary beneficiaries 50/30/20. | M58: 50%, 30%, 20% | N58: 1. Remove the 30% beneficiary. 2. Read the running total and error. 3. Edit another to 50%. 4. Read the total again. | O58: - Total becomes 70% and an allocation error appears. - After edit the total recomputes to 100% and the error clears. | P58: beneficiary-allocation-summary, beneficiary-error-summary, beneficiary-allocation-input | Q58: BeneficiaryPage | R58: Screenshot after remove and after edit. | T58: D, S | U58: Ready | V58: Not run
A59: TC-DOC-001 | B59: Document upload & validation summary | C59: DOC-V01 | D59: Valid KYC document can be uploaded | E59: R-DOC-02 | G59: UI + API | H59: Smoke | I59: P1 | J59: Smoke test; highest linked risk R-DOC-02 (score 6) | K59: @smoke @regression @api @documents | L59: Documents step. | M59: valid.pdf, valid.jpg, valid.png (<= 5 MB); document type KYC_ID | N59: 1. Upload each valid file. 2. Observe status. 3. Reload the page. 4. Read GET .../documents (if endpoint exists). | O59: - Uploaded status and file name are displayed. - Status persists after reload. - Document appears once in the API list. | P59: documents-page, document-type-select (KYC_ID, ADDRESS_PROOF, INCOME_PROOF, OTHER), document-upload-kyc (file input), document-upload-button, documents-table, document-row-{id}, document-delete-{id}, documents-continue-review-button | Q59: DocumentUploadPage, fileUploadHelper | R59: Screenshot of status. | T59: M, S | U59: Ready | V59: Not run
A60: TC-DOC-002 | B60: Document upload & validation summary | C60: DOC-V02 | D60: Unsupported file type is rejected | E60: R-DOC-01 | G60: UI + API | H60: Negative | I60: P3 | J60: highest linked risk R-DOC-01 (score 4) | K60: @regression @api @documents | L60: Documents step. | M60: invalid.exe, invalid.txt, and a text file renamed .pdf; use types ADDRESS_PROOF / INCOME_PROOF / OTHER (KYC_ID is covered by CLI-V09) | N60: 1. Upload each unsupported file. 2. Observe error. 3. Check the document list and API. | O60: - "Unsupported document format. Accepted formats are PDF, JPG, and PNG." is shown. - Nothing is stored; documents-table unchanged. | P60: documents-page, document-type-select (KYC_ID, ADDRESS_PROOF, INCOME_PROOF, OTHER), document-upload-kyc (file input), document-upload-button, documents-table, document-row-{id}, document-delete-{id}, documents-continue-review-button | Q60: DocumentUploadPage | R60: Screenshot of error. | T60: S | U60: Ready | V60: Not run
A61: TC-DOC-003 | B61: Document upload & validation summary | C61: DOC-V03 | D61: File above maximum size is rejected | E61: R-DOC-01 | G61: UI + API | H61: Boundary | I61: P3 | J61: highest linked risk R-DOC-01 (score 4) | K61: @regression @api @documents | L61: Documents step. | M61: Limit 5 MB (5,120 KB): 5,121 KB file rejected with "Document size exceeds the allowed limit."; file at 5,120 KB accepted. Check that PHP upload_max_filesize/post_max_size is not lower than 5 MB, otherwise the failure message differs. | N61: 1. Generate the oversize file at run time. 2. Upload it. 3. Upload a file at the limit. | O61: - A size error is shown for the oversize file and nothing is stored. - The file at the limit is accepted. | P61: documents-page, document-type-select (KYC_ID, ADDRESS_PROOF, INCOME_PROOF, OTHER), document-upload-kyc (file input), document-upload-button, documents-table, document-row-{id}, document-delete-{id}, documents-continue-review-button | Q61: DocumentUploadPage, fileUploadHelper | R61: Screenshot of size error. | S61: OI-09 | T61: S, V | U61: Needs confirmation | V61: Not run
A62: TC-DOC-004 | B62: Document upload & validation summary | C62: DOC-V04 | D62: Missing mandatory document blocks submission | E62: R-KYC-02 | F62: SDC-06 | G62: UI + API | H62: Negative | I62: P1 | J62: highest linked risk R-KYC-02 (score 9) | K62: @regression @api @documents @SDC-06 | L62: Application complete except mandatory document. | M62: No document uploaded | N62: 1. Skip the upload. 2. Open the review page. 3. Try to submit. 4. Call POST .../submit. | O62: - Validation summary lists the missing document. - Submit is blocked in the UI. - API submit is rejected and status stays Draft. | P62: Required document type KYC_ID; message "KYC ID document upload is required."; review-validation-errors | Q62: DocumentUploadPage, ReviewPage, apiClient | R62: Screenshot of summary; API response. | T62: S | U62: Ready | V62: Not run
A63: TC-DOC-005 | B63: Document upload & validation summary | C63: VAL-V01 | D63: Validation summary lists all unresolved errors, grouped | E63: R-DOC-03; R-BEN-06 | G63: UI | H63: Functional | I63: P2 | J63: highest linked risk R-BEN-06 (score 6) | K63: @regression @documents | L63: Application with only client information completed. | M63: Incomplete application | N63: 1. Open the review page. 2. Read the validation summary. | O63: - Validation summary lists each unresolved section (client, address, contact, KYC, financial, compliance, product, beneficiaries, documents). - Errors are grouped by section. | P63: review-page, review-validate-button, review-validation-errors | Q63: ReviewPage | R63: Screenshot of summary. | T63: S | U63: Ready | V63: Not run
A64: TC-DOC-006 | B64: Document upload & validation summary | C64: VAL-V02 | D64: Clicking a validation error navigates to the field | E64: R-DOC-03 | G64: UI | H64: Functional | I64: P3 | J64: highest linked risk R-DOC-03 (score 4) | K64: @regression @documents | L64: Review page with at least three unresolved errors. | M64: Incomplete application | N64: 1. Click each of the first three errors. 2. Observe the page. | O64: - The related section opens. - The relevant field is focused or highlighted. | P64: review-validation-errors (links to sections) | Q64: ReviewPage | R64: Screenshot after each click. | S64: OI-15 | T64: D, V | U64: Needs confirmation | V64: Not run
A65: TC-DOC-007 | B65: Document upload & validation summary | C65: VAL-V03 | D65: Submit stays disabled until critical errors are resolved | E65: R-WF-02 | F65: SDC-17 | G65: UI + API | H65: Negative | I65: P1 | J65: highest linked risk R-WF-02 (score 9) | K65: @regression @api @documents @SDC-17 | L65: Review page with a critical error. | M65: Application with one critical error | N65: 1. Open /applications/{id}/review with a critical error. 2. Read the state of review-submit-application-button. 3. Fix errors one by one; click review-validate-button and reload the review page after each fix. 4. With one error left POST /api/applications/{id}/validate and /submit. | O65: - Submit button is disabled while any review error exists. - It becomes enabled only after all errors are resolved (review-validation-passed shows). - API submit returns 422 "Validation failed" while an error remains. | P65: review-submit-application-button (disabled while review errors exist), review-validate-button, review-validation-passed | Q65: ReviewPage, apiClient | R65: Screenshot of disabled button; API response. | T65: S | U65: Ready | V65: Not run
A66: TC-WF-001 | B66: Submission & status tracking | C66: WF-V01 | D66: Agent can save an incomplete application as draft | E66: R-WF-01 | F66: SDC-16 | G66: UI | H66: Functional | I66: P1 | J66: highest linked risk R-WF-01 (score 9) | K66: @regression @workflow @SDC-16 | L66: Logged in as {learnerUser}. In this build the draft is created by application-create-draft-button and each Save & Continue stores the step. | M66: Client + address data | N66: 1. Open /applications/new and click application-create-draft-button. 2. Fill and save the client step; stop there. 3. Open /dashboard (nav-dashboard-link). | O66: - Dashboard shows the application with status DRAFT. - The draft summary count increased by 1. | P66: application-create-draft-button, client-save-continue-button, nav-dashboard-link, application-status-{id} | Q66: ClientInformationPage, DashboardPage | R66: Screenshot of draft row. | T66: S | U66: Ready | V66: Not run
A67: TC-WF-002 | B67: Submission & status tracking | C67: WF-V02 | D67: Draft can be resumed with saved data | E67: R-WF-01 | F67: SDC-16 | G67: UI + API | H67: Functional | I67: P1 | J67: highest linked risk R-WF-01 (score 9) | K67: @regression @api @workflow @SDC-16 | L67: Draft from WF-V01 style setup. | M67: Known field values | N67: 1. Log out and log in again. 2. Resume the draft. 3. Compare every field with the values entered. 4. Compare with GET .../client. | O67: - All entered values are restored in the UI. - API data equals UI data. | P67: application-open-{id}; GET /api/applications/{id}/client | Q67: DashboardPage, ClientInformationPage, apiClient | R67: Field comparison table. | T67: S | U67: Ready | V67: Not run
A68: TC-WF-003 | B68: Submission & status tracking | C68: WF-V03 | D68: Valid application can be submitted successfully (full E2E) | E68: R-WF-03 | G68: UI + API | H68: E2E | I68: P1 | J68: Smoke test; highest linked risk R-WF-03 (score 6) | K68: @smoke @regression @e2e @api @workflow | L68: Valid agent logged in. | M68: Two data-driven flows: TD-E2E-01 (individual beneficiary, ADB rider) and TD-E2E-02 (trust primary, minor secondary with guardian, critical illness rider with questionnaire) | N68: 1. Login and open dashboard. 2. Start new application. 3. Complete client, address, KYC and upload documents. 4. Select product and configure policy. 5. Add rider(s). 6. Add beneficiaries totalling 100%. 7. Open review with zero errors and submit. 8. Read reference number. 9. Open dashboard. | O68: - Confirmation page shows confirmation-reference-number matching WL + yyyymmdd + 5 digits (e.g. WL2026102500123). - Dashboard row shows SUBMITTED. - GET /api/applications/{id}/status shows SUBMITTED with a history entry "Application submitted successfully." | P68: All page ids; confirmation-reference-number, confirmation-view-status-link, status-current-value; reference regex /^WL\d{8}\d{5}$/ | Q68: All page objects | R68: Screenshots at each stage; trace; reference number in report. | T68: S, M | U68: Ready | V68: Not run
A69: TC-WF-004 | B69: Submission & status tracking | C69: WF-V04 | D69: Submitted application becomes read-only | E69: R-WF-04 | G69: UI + API | H69: Negative | I69: P2 | J69: highest linked risk R-WF-04 (score 6) | K69: @regression @api @workflow | L69: A submitted application exists. | M69: {submittedAgent} SUBMITTED application WL202605170003 (seeded) | N69: 1. Open the submitted application. 2. Check all inputs. 3. Attempt to edit via API. | O69: - Fields are not editable; no save/submit action available. - API rejects edit requests. | P69: Submitted application pages /applications/{id}/client etc.; POST edits | Q69: ApplicationStatusPage, apiClient | R69: Screenshot; API response. | S69: OI-15 | T69: D, V | U69: Needs confirmation | V69: Not run
A70: TC-WF-005 | B70: Submission & status tracking | C70: WF-V05 | D70: Confirmation message appears after submission | E70: R-WF-05 | G70: UI | H70: Functional | I70: P3 | J70: highest linked risk R-WF-05 (score 2) | K70: @regression @workflow | L70: Complete application ready to submit. | M70: Complete application | N70: 1. Submit. 2. Read the confirmation page. | O70: - Success message and reference number are shown. - Confirmation-email simulation message appears if present [V]. | P70: submission-confirmation-page, confirmation-reference-number, confirmation-dashboard-link | Q70: ConfirmationPage | R70: Screenshot of confirmation. | T70: S | U70: Ready | V70: Not run
A71: TC-WF-006 | B71: Submission & status tracking | C71: WF-V06 | D71: Dashboard status updates after submission | E71: R-WF-03; R-DASH-02 | F71: SDC-18 | G71: UI + API | H71: Reconciliation | I71: P1 | J71: highest linked risk R-DASH-02 (score 9) | K71: @regression @api @workflow @SDC-18 | L71: A draft that is ready to submit. | M71: Complete application | N71: 1. Note draft counts. 2. Submit. 3. Open the dashboard. 4. Check the Submitted filter and the Draft filter. | O71: - Row status is Submitted. - It appears under Submitted and not under Draft. - Counts update. | P71: application-status-{id}, dashboard-summary-draft, dashboard-summary-submitted | Q71: DashboardPage | R71: Screenshot of dashboard after submit. | T71: S | U71: Ready | V71: Not run
A72: TC-WF-007 | B72: Submission & status tracking | C72: WF-V07 | D72: Application detail status matches the API response | E72: R-DASH-02 | F72: SDC-18 | G72: UI + API | H72: Reconciliation | I72: P1 | J72: highest linked risk R-DASH-02 (score 9) | K72: @regression @api @workflow @SDC-18 | L72: A submitted application. | M72: Submitted application | N72: 1. Open /applications/:id/status. 2. Read current status and history. 3. Call GET .../status. 4. Compare. | O72: - Current status equals the API. - History entries match in order and timestamps. | P72: status-page, status-current-value, status-reference-number, status-history-table, status-row-{id}; GET /api/applications/{id}/status (application_status, status_history[]) | Q72: ApplicationStatusPage, apiClient | R72: History table. | T72: S | U72: Ready | V72: Not run
A73: TC-API-001 | B73: API tests | C73: API-V01 | D73: Products API returns 200 and the expected schema | E73: R-API-03; R-PROD-05 | G73: API | H73: Smoke | I73: P1 | J73: Smoke test; highest linked risk R-PROD-05 (score 4) | K73: @smoke @regression @api | L73: Authenticated API context. | M73: Expect 5 active products with product_code, product_name, eligibility_age_min/max, face_value_min/max, base_rate_per_1000, is_active | N73: 1. GET /api/products with X-API-Key. 2. Assert status code, envelope and item schema. 3. GET /api/products?search=Secure. | O73: - HTTP 200 with status "success". - data has 5 items with the listed keys and types. - search filters by product name. | P73: GET /api/products. Header X-API-Key (env INSURANCE_API_KEY). Agent chosen with agent_email (default is learner001!). Envelope {status,message,data|errors}. | Q73: apiClient | R73: Response body attached. | T73: S | U73: Ready | V73: Not run
A74: TC-API-002 | B74: API tests | C74: API-V02 | D74: Application APIs require authorization | E74: R-API-02; R-AUTH-06 | G74: API | H74: Smoke | I74: P1 | J74: Smoke test; highest linked risk R-AUTH-06 (score 6) | K74: @smoke @regression @api | L74: No API key (and a wrong key). | M74: X-API-Key missing; X-API-Key: wrong | N74: 1. GET /api/applications without X-API-Key. 2. Repeat with a wrong key. 3. POST /api/applications/{id}/submit without key. 4. GET /api/health without key (public). | O74: - Protected endpoints return 401 {status:"error", message:"Unauthorized"}. - No application data is returned. - Health returns 200 without a key. | P74: GET /api/applications, POST /api/applications/{id}/submit. GET /api/health is public. | Q74: apiClient | R74: Status codes and bodies attached. | T74: S | U74: Ready | V74: Not run
A75: TC-API-003 | B75: API tests | C75: API-V03 | D75: Client API rejects invalid DOB | E75: R-CLI-01; R-CLI-02; R-API-01 | F75: SDC-04; SDC-05; SDC-19 | G75: API | H75: Negative | I75: P1 | J75: highest linked risk R-CLI-01 (score 9) | K75: @regression @api @SDC-04 @SDC-05 @SDC-19 | L75: Draft created by POST /api/applications (agent_email = {learnerUser}). Payload field names assumed equal to the UI form (first_name, last_name, date_of_birth, gender, marital_status, nationality, occupation, employer_name, employer_address): confirm at first run. | M75: DOB future, age 17, age 66; valid DOB | N75: 1. POST client data with each invalid DOB. 2. GET the client data after each. 3. POST with a valid DOB. | O75: - Future DOB and out-of-range ages are rejected (422, status "error", errors keyed by field); capture exact bodies. - GET client afterwards shows no invalid DOB. - Valid DOB returns success. UI and API outcomes agree. | P75: POST /api/applications/{id}/client. Header X-API-Key (env INSURANCE_API_KEY). Agent chosen with agent_email (default is learner001!). Envelope {status,message,data|errors}. | Q75: apiClient | R75: Request/response pairs. | S75: OI-18 | T75: S, V | U75: Needs confirmation | V75: Not run
A76: TC-API-004 | B76: API tests | C76: API-V04 | D76: Validation API returns beneficiary allocation error | E76: R-BEN-01; R-API-01 | F76: SDC-13; SDC-19 | G76: API | H76: Negative | I76: P1 | J76: highest linked risk R-BEN-01 (score 9) | K76: @regression @api @SDC-13 @SDC-19 | L76: Application with beneficiaries added. | M76: Primary 90%, 110%, 100% | N76: 1. Set up beneficiaries for each total. 2. POST .../validate. 3. Read the error structure. | O76: - 90% and 110% return 422 "Validation failed" with an error under beneficiaries about the primary allocation (expected wording: "Primary beneficiary allocation must total exactly 100%"). - 100% returns no beneficiaries error. | P76: POST /api/applications/{id}/validate. Header X-API-Key (env INSURANCE_API_KEY). Agent chosen with agent_email (default is learner001!). Envelope {status,message,data|errors}. | Q76: apiClient | R76: Validate response bodies. | S76: OI-18 | T76: S | U76: Needs confirmation | V76: Not run
A77: TC-API-005 | B77: API tests | C77: API-V05 | D77: Submission API rejects an incomplete application | E77: R-WF-02; R-KYC-02; R-API-01 | F77: SDC-17; SDC-06; SDC-19 | G77: API | H77: Negative | I77: P1 | J77: highest linked risk R-WF-02 (score 9) | K77: @regression @api @SDC-17 @SDC-06 @SDC-19 | L77: Incomplete draft. | M77: Draft missing documents and beneficiaries | N77: 1. POST .../submit. 2. Read the response. 3. GET .../status. | O77: - 422 "Validation failed" with an errors bag per section. - GET status still DRAFT; application_reference_number empty. | P77: POST /api/applications/{id}/submit; GET .../status. Header X-API-Key (env INSURANCE_API_KEY). Agent chosen with agent_email (default is learner001!). Envelope {status,message,data|errors}. | Q77: apiClient | R77: Response body; status response. | T77: S | U77: Ready | V77: Not run
A78: TC-API-006 | B78: API tests | C78: API-V06 | D78: Application status API matches the dashboard | E78: R-DASH-02 | F78: SDC-18 | G78: UI + API | H78: Reconciliation | I78: P1 | J78: highest linked risk R-DASH-02 (score 9) | K78: @regression @api @SDC-18 | L78: Agent with applications. | M78: {validAgent} | N78: 1. GET .../status for an application. 2. Read the dashboard status for the same ID. 3. Compare. | O78: - Statuses are equal for the same agent and application. | P78: GET /api/applications/{id}/status -> {application_id, application_reference_number, application_status, current_step, status_history[]}; use agent_email of the UI user | Q78: apiClient, DashboardPage | R78: ID / UI / API status table. | T78: S | U78: Ready | V78: Not run
A79: TC-API-007 | B79: API tests | C79: API-V07 | D79: Product API supports product detail retrieval | E79: R-PROD-05; R-API-03 | G79: UI + API | H79: Reconciliation | I79: P3 | J79: highest linked risk R-PROD-05 (score 4) | K79: @regression @api | L79: Product selected in the UI. | M79: Selected product ID | N79: 1. Read name, limits, terms and eligibility on the details page. 2. GET /api/products/{id}. 3. Compare. | O79: - All compared fields are equal. - Unknown product ID returns 404. | P79: GET /api/products/{product}: id is the numeric product id; unknown id -> 404 | Q79: apiClient, ProductCatalogPage | R79: Comparison table. | T79: S | U79: Ready | V79: Not run
A80: TC-API-008 | B80: API tests | C80: API-V08 | D80: Applications API returns only the logged-in agent records | E80: R-DASH-01 | G80: API | H80: Authorization | I80: P2 | J80: highest linked risk R-DASH-01 (score 6) | K80: @regression @api | L80: Two agents with applications. | M80: agent.valid and agent.draft (agent_email) | N80: 1. GET /api/applications?agent_email=agent.valid@insurance.test and agent.draft@insurance.test. 2. Compare the two lists. 3. GET /api/applications/{id} for an id owned by the other agent and note the result. | O80: - The lists are disjoint. - Per Problem Statement 2.2 an agent must only see own records: record the status/body of the cross-agent GET and assess against that rule (do not assume). | P80: GET /api/applications?agent_email=<agent>; GET /api/applications/{id} | Q80: apiClient | R80: Status codes. | T80: D, S | U80: Ready | V80: Not run
A81: TC-API-009 | B81: API tests | C81: API-P01 | D81: Documents API validates type and size | E81: R-DOC-01; R-DOC-02 | G81: API | H81: Negative | I81: P2 | J81: highest linked risk R-DOC-02 (score 6) | K81: @regression @api | L81: Draft application. PROPOSED test. | M81: valid PDF; invalid.exe; oversize file | N81: 1. POST the valid PDF. 2. POST the invalid type. 3. POST the oversize file. 4. GET document status. | O81: - Valid PDF/JPG/PNG returns 201 "Document uploaded". - Invalid type or > 5 MB returns 422 "Document validation failed". - KYC_ID upload satisfies the required-document rule. | P81: POST /api/applications/{id}/documents multipart: document_type (KYC_ID|ADDRESS_PROOF|INCOME_PROOF|OTHER), document (file). Header X-API-Key (env INSURANCE_API_KEY). Agent chosen with agent_email (default is learner001!). Envelope {status,message,data|errors}. | Q81: apiClient, fileUploadHelper | R81: Responses. | T81: S | U81: Ready | V81: Not run
A82: TC-API-010 | B82: API tests | C82: API-P02 | D82: Login API status codes and response schema | E82: R-AUTH-01; R-AUTH-02 | F82: SDC-01; SDC-02 | G82: API | H82: Functional | I82: P1 | J82: highest linked risk R-AUTH-01 (score 9) | K82: @regression @api @SDC-01 @SDC-02 | L82: Seeded users. PROPOSED test. | M82: Valid, wrong password, blank, locked user | N82: 1. POST /api/login with {validAgent}. 2. POST with a wrong password. 3. POST with blank body. 4. POST with {lockedAgent}. | O82: - Valid: 200, message "Login validated successfully", data {user_id,name,email,role,learner_code,account_status}; no token or cookie. - Wrong password: 401 "Invalid credentials". - Blank: 422 with field errors. - Locked: 403 "Account locked". | P82: POST /api/login {email,password} (not /api/auth/login). Success has no token. | Q82: apiClient | R82: Responses. | T82: M, S | U82: Ready | V82: Not run

Sheet Test_Data
A1: Data ID | B1: Name / placeholder | C1: Values or generation rule | D1: Used by (validation IDs) | E1: Status
A2: TD-USR-01 | B2: {validAgent} | C2: agent.valid@insurance.test. Primary happy path and regression. Owns seeded DRAFT WL202605170001. (Lab Manual 3.1) | D2: AUTH-V01, V02, V04, DASH-*, API-V08 | E2: Confirmed (M)
A3: TD-USR-02 | B3: {agent2} | C3: agent.draft@insurance.test. Second agent with own draft; used for isolation checks. | D3: DASH-V02, API-V08 | E3: Confirmed (M)
A4: TD-USR-03 | B4: {newAgent} | C4: agent.new@insurance.test. Fresh user with no applications. | D4: DASH-V03 | E4: Confirmed (M)
A5: TD-USR-04 | B5: {submittedAgent} | C5: agent.submitted@insurance.test. Owns SUBMITTED WL202605170003 and REQUIRES_INFO WL202605170004 (seed). | D5: DASH-V05, WF-V04 | E5: Confirmed (M, S)
A6: TD-USR-05 | B6: {lockedAgent} | C6: agent.locked@insurance.test. Dedicated locked user (answer to Q-10). | D6: AUTH-V06, API-P02 | E6: Confirmed (M, A)
A7: TD-USR-06 | B7: {learnerUser} | C7: Your assigned learnerNNN@insurance.test (NNN 001-030). Used for all write flows and the E2E. NOTE: API default agent is learner001; always pass agent_email. | D7: WF-*, DASH-V06, API-* setup | E7: Set in .env (A)
A8: TD-USR-07 | B8: {disposableAgent} | C8: Spare learner-pool account on your own VM, used to lock the account and for password-policy checks. Confirm with mentor; fallback agent.new@insurance.test (then run DASH-V03 first). | D8: AUTH-V07, AUTH-V08 | E8: Confirm with mentor
A9: TD-USR-08 | B9: Out of scope | C9: admin@insurance.test and agent.mfa@insurance.test exist in the seed but are NOT in the Lab Manual; admin and MFA are out of scope (Q-06, Q-15). Do not use unless the mentor says so. | D9: - | E9: Out of scope
A10: TD-DOB-01 | B10: Age 17 (reject) | C10: DOB = today - 18y + 1 day. | D10: CLI-V03, API-V03 | E10: Ready
A11: TD-DOB-02 | B11: Age 18 (accept) | C11: DOB = today - 18y. Rule is inclusive. | D11: CLI-P01 | E11: Ready (S)
A12: TD-DOB-03 | B12: Age 40 (valid) | C12: DOB = today - 40y. | D12: CLI-V01, WF-V03 | E12: Ready
... A33: TD-GEN-01 | B33: Naming convention | C33: Created data uses QA_<runId>; tests change only what they created; seeded records are never edited; no database reset (Lab Manual section 8). | D33: All stateful tests | E33: Rule

Sheet Calculators
A1: Premium and affordability calculators
A2: Formula source: application seed data and premium service constants (S). Annual premium = face value / 1000 x rate; period premium = annual / 12, 4, 2 or 1, rounded to 2 decimals. Confirm against the UI at first run (tolerance 0.01).
A4: Base premium
A5: Product | B5: Face value | C5: Rate per 1,000 | D5: Annual premium | E5: Monthly | F5: Quarterly | G5: Semi-annual | H5: Annual | I5: Check vs seed data
A6: SecureLife (WL_SECURE_BASIC), min | B6: 100000 | C6: 4.75 | D6: =B6/1000*C6 -> 475 | E6: =ROUND(D6/12,2) -> 39.58 | F6: =ROUND(D6/4,2) -> 118.75 | G6: =ROUND(D6/2,2) -> 237.5 | H6: =ROUND(D6,2) -> 475
A7: SecureLife, seed example | B7: 250000 | C7: 4.75 | D7: =B7/1000*C7 -> 1187.5 | E7: =ROUND(D7/12,2) -> 98.96 | F7: =ROUND(D7/4,2) -> 296.88 | G7: =ROUND(D7/2,2) -> 593.75 | H7: =ROUND(D7,2) -> 1187.5 | I7: =IF(E7=98.96,"matches seed monthly 98.96","DIFFERENT") -> matches seed monthly 98.96
A8: WealthBuilder (WL_WEALTH_BUILDER), min | B8: 150000 | C8: 5.35 | D8: =B8/1000*C8 -> 802.5 | E8: =ROUND(D8/12,2) -> 66.88 | F8: =ROUND(D8/4,2) -> 200.63 | G8: =ROUND(D8/2,2) -> 401.25 | H8: =ROUND(D8,2) -> 802.5
A9: WealthBuilder, seed example | B9: 350000 | C9: 5.35 | D9: =B9/1000*C9 -> 1872.5 | E9: =ROUND(D9/12,2) -> 156.04 | F9: =ROUND(D9/4,2) -> 468.13 | G9: =ROUND(D9/2,2) -> 936.25 | H9: =ROUND(D9,2) -> 1872.5 | I9: =IF(F9=468.13,"matches seed quarterly 468.13","DIFFERENT") -> matches seed quarterly 468.13
A10: Elite Legacy (WL_ELITE_LEGACY), min | B10: 500000 | C10: 6.1 | D10: =B10/1000*C10 -> 3050 | E10: =ROUND(D10/12,2) -> 254.17 | F10: =ROUND(D10/4,2) -> 762.5 | G10: =ROUND(D10/2,2) -> 1525 | H10: =ROUND(D10,2) -> 3050
A11: FlexiPay (WL_FLEXI_PAY), min | B11: 100000 | C11: 5 | D11: =B11/1000*C11 -> 500 | E11: =ROUND(D11/12,2) -> 41.67 | F11: =ROUND(D11/4,2) -> 125 | G11: =ROUND(D11/2,2) -> 250 | H11: =ROUND(D11,2) -> 500
A12: Guaranteed Return (WL_GUARANTEED_RETURN), min | B12: 200000 | C12: 5.85 | D12: =B12/1000*C12 -> 1170 | E12: =ROUND(D12/12,2) -> 97.5 | F12: =ROUND(D12/4,2) -> 292.5 | G12: =ROUND(D12/2,2) -> 585 | H12: =ROUND(D12,2) -> 1170
A14: Rider premium
A15: Rider | B15: Coverage | C15: Rate per 1,000 | D15: Annual premium | E15: Monthly | F15: Quarterly | G15: Semi-annual | H15: Annual | I15: Note
A16: RIDER_ADB, coverage = base 250,000 | B16: 250000 | C16: 0.85 | D16: =B16/1000*C16 -> 212.5 | E16: =ROUND(D16/12,2) -> 17.71 | F16: =ROUND(D16/4,2) -> 53.13 | G16: =ROUND(D16/2,2) -> 106.25 | H16: =ROUND(D16,2) -> 212.5 | I16: Seed: agent.valid rider premium 17.71 monthly
A17: RIDER_DISABILITY | B17: 250000 | C17: 1.1 | D17: =B17/1000*C17 -> 275 | E17: =ROUND(D17/12,2) -> 22.92 | F17: =ROUND(D17/4,2) -> 68.75 | G17: =ROUND(D17/2,2) -> 137.5 | H17: =ROUND(D17,2) -> 275
A18: RIDER_TERM_ADDON | B18: 250000 | C18: 1.25 | D18: =B18/1000*C18 -> 312.5 | E18: =ROUND(D18/12,2) -> 26.04 | F18: =ROUND(D18/4,2) -> 78.13 | G18: =ROUND(D18/2,2) -> 156.25 | H18: =ROUND(D18,2) -> 312.5
A19: RIDER_CRITICAL_ILLNESS (max 500,000) | B19: 250000 | C19: 1.6 | D19: =B19/1000*C19 -> 400 | E19: =ROUND(D19/12,2) -> 33.33 | F19: =ROUND(D19/4,2) -> 100 | G19: =ROUND(D19/2,2) -> 200 | H19: =ROUND(D19,2) -> 400
A20: RIDER_HOSPITAL_CASH (fixed, max 100,000) | B20: 100000 | C20: 0.65 | D20: =B20/1000*C20 -> 65 | E20: =ROUND(D20/12,2) -> 5.42 | F20: =ROUND(D20/4,2) -> 16.25 | G20: =ROUND(D20/2,2) -> 32.5 | H20: =ROUND(D20,2) -> 65
A22: Affordability rule
A23: Threshold (% of annual income) | B23: 20 | C23: Source: app config DEMO_AFFORDABILITY_PERCENTAGE = 20 (S). Confirm that annual premium is the compared value.
A24: Case | B24: Annual income | C24: Limit | D24: Annual premium | E24: Result | I24: Expected message
A25: Low income, SecureLife 250k monthly | B25: 5000 | C25: =B25*$B$23/100 -> 1000 | D25: =D7 -> 1187.5 | E25: =IF(D25>C25,"EXCEEDS","OK") -> EXCEEDS | I25: =IF(E25="EXCEEDS","Premium exceeds affordability threshold.","none") -> Premium exceeds affordability threshold.
A26: Adequate income, same policy | B26: 50000 | C26: =B26*$B$23/100 -> 10000 | D26: =D7 -> 1187.5 | E26: =IF(D26>C26,"EXCEEDS","OK") -> OK | I26: =IF(E26="EXCEEDS","Premium exceeds affordability threshold.","none") -> none
A27: Low income, Elite Legacy 500k | B27: 10000 | C27: =B27*$B$23/100 -> 2000 | D27: =D10 -> 3050 | E27: =IF(D27>C27,"EXCEEDS","OK") -> EXCEEDS | I27: =IF(E27="EXCEEDS","Premium exceeds affordability threshold.","none") -> Premium exceeds affordability threshold.
A30: Blue = input. Black = formula. Change the inputs to build extra test data; expected values update.

Sheet Environment_Facts
A1: Environment facts (replaces assumptions with sources)
A2: Sources: M = Lab Manual v1.0, A = learner answers, S = application source, V = verify in UI. Passwords and the API key are NOT recorded here (see .env).
A4: 1. Access
A5: Item | B5: Value | C5: Note | E5: Source
A6: Insurance app | B6: http://<vm-ip>:8081/login | C6: Q-01 answered: port 8081. Env: INSURANCE_BASE_URL | E6: M, A
A7: FinServe app | B7: http://<vm-ip>:8082/login | C7: Different project, not used here | E7: M
A8: API base | B8: http://<vm-ip>:8081/api | C8: Header X-API-Key from .env (INSURANCE_API_KEY). GET /api/health is public. | E8: M, S
A9: Platform | B9: Linux combined lab instance | C9: Manual v1.0 says Linux; the earlier Quick Start Manual described a Windows VM with C:\qa-lab. Confirm which applies to your VM. | E9: M, V
A10: Browsers | B10: Chromium default; Firefox and WebKit configurable | C10: Q-12: playwright.config projects selected by env BROWSERS (default chromium). | E10: A
A11: Workers | B11: Start with 1 worker | C11: VM is dedicated (Q-14) but earlier assignments showed concurrency artifacts under load; raise workers only for read-only suites. | E11: A, V
A12: Session lifetime | B12: 120 minutes | C12: Session timeout testing is out of scope (Q-11). | E12: S, A
A13: Database | B13: MySQL (per app config); .sql dump found in db-dumps | C13: Read access still to be confirmed; do not run resets (Manual section 8). | E13: S, A
A15: 2. Seed users (usernames only; password and key in .env)
A16: Account | B16: Use | C16: Seed data / note | E16: Source
A17: agent.valid@insurance.test | B17: Primary happy path | C17: Seeded DRAFT WL202605170001 (step BENEFICIARIES) | E17: M, S
A18: agent.new@insurance.test | B18: Fresh user | C18: No applications | E18: M, S
A19: agent.draft@insurance.test | B19: Draft scenario | C19: Seeded DRAFT WL202605170002 (step DOCUMENTS) | E19: M, S
A20: agent.submitted@insurance.test | B20: Submitted scenario | C20: SUBMITTED WL202605170003; REQUIRES_INFO WL202605170004 | E20: M, S
A21: agent.locked@insurance.test | B21: Locked login | C21: account_status LOCKED | E21: M, S
A22: learner001..learner030@insurance.test | B22: Assigned learner pool | C22: Use your assigned account for write flows | E22: M
A24: 3. API contract (from source)
A25: Topic | B25: Fact | C25: Test impact | E25: Source
A26: Authentication | B26: Static X-API-Key. Missing/wrong key -> 401 {"status":"error","message":"Unauthorized"}. No per-user token. | C26: API-V02, setup helper | E26: S
A27: Agent context | B27: agent_email (or user_id) selects the agent; DEFAULT is learner001@insurance.test. | C27: Always pass agent_email equal to the UI user | E27: S
A28: Envelope | B28: Success {status:"success", message, data}; error {status:"error", message, errors} | C28: Assertion helper | E28: S
A29: POST /api/login | B29: 200 "Login validated successfully" with user fields; 401 "Invalid credentials"; 403 "Account locked"; 422 blank | C29: API-P02, AUTH-V06 | E29: S
A30: POST /api/applications | B30: 201 "Draft application created" (status DRAFT, step CLIENT, MONTHLY, WHOLE_LIFE) | C30: Fast setup for UI tests (OI-05 closed) | E30: S
A31: Other endpoints | B31: GET /applications, /applications/{id}, /{id}/client, /{id}/beneficiaries, /{id}/status; POST /{id}/client, address-contact, kyc-financial, product, riders, beneficiaries, documents, validate, submit; GET /products, /products/{id}, /riders | C31: API-V01..V08, P01, P02 | E31: S
A32: Validate / submit errors | B32: 422 "Validation failed" with errors per section | C32: API-V04, V05, VAL-V03 | E32: S
A33: Status payload | B33: application_id, application_reference_number, application_status, current_step, status_history[] | C33: API-V06, WF-V07 | E33: S
A35: 4. Business limits and rules
A36: Rule | B36: Value | C36: Message / note | E36: Source
A37: Client age | B37: 18 to 65 inclusive | C37: "Client age must be between 18 and 65 years." | E37: A, S
A38: Future DOB | B38: Not allowed | C38: "Future date of birth is not allowed." | E38: S
A39: Max riders | B39: 4 per application | C39: Message to capture | E39: S
A40: Affordability | B40: Annual premium <= 20% of annual income | C40: "Premium exceeds affordability threshold." | E40: S, V
A41: Documents | B41: PDF, JPG, PNG; max 5 MB; required type KYC_ID; types KYC_ID, ADDRESS_PROOF, INCOME_PROOF, OTHER | C41: "Unsupported document format. Accepted formats are PDF, JPG, and PNG." / "Document size exceeds the allowed limit." / "KYC ID document upload is required." | E41: S
A42: Beneficiaries | B42: Primary total exactly 100%; at least one primary; minor needs guardian | C42: "Primary beneficiary allocation must total exactly 100%." / "At least one primary beneficiary is required." / "Guardian details are required for minor beneficiaries." | E42: S
A43: Password policy | B43: 12+ chars; upper; lower; digit; one of !@#$%^&*; no email username; no common/sequential pattern; no 3 repeated characters | C43: Rule-specific messages, e.g. "Password must be at least 12 characters." | E43: S
A44: SSN / ID masking | B44: Characters except last 4 replaced by *; stored masked plus hash | C44: Q-18 unanswered: derived, confirm in UI | E44: S, V
A45: Phone / ZIP / state | B45: US formats (see Test_Data) | C45: US states + DC | E45: S
A46: Reference number | B46: WL + yyyymmdd + 5 digits (generated); seed examples use 4 digits | C46: Regex /^WL\d{13}$/ for new applications | E46: S, V
A47: Premium frequency | B47: MONTHLY, QUARTERLY, SEMI_ANNUAL, ANNUAL; policy term WHOLE_LIFE, TO_AGE_100; payment term 1-100 years | C47: See Calculators | E47: S
... A49: Lockout | B49: Five failed attempts (docs); lock is time-based (locked_until) | C49: Duration to observe; unlock is an admin action (out of scope) | E49: D, S, V
A51: 5. Products (seed data)
A52: Product (code) | B52: Eligibility age | C52: Face value min / max | D52: Rate per 1,000 | E52: Source
A53: SecureLife Whole Life (WL_SECURE_BASIC) | B53: 18-65 | C53: 100,000 / 1,000,000 | D53: 4.75 | E53: S
A54: WealthBuilder Whole Life (WL_WEALTH_BUILDER) | B54: 21-60 | C54: 150,000 / 1,500,000 | D54: 5.35 | E54: S
A55: Elite Legacy Whole Life (WL_ELITE_LEGACY) | B55: 30-65 | C55: 500,000 / 5,000,000 | D55: 6.10 | E55: S
A56: FlexiPay Whole Life (WL_FLEXI_PAY) | B56: 18-62 | C56: 100,000 / 1,200,000 | D56: 5.00 | E56: S
A57: Guaranteed Return Whole Life (WL_GUARANTEED_RETURN) | B57: 25-55 | C57: 200,000 / 2,000,000 | D57: 5.85 | E57: S
A59: 6. Riders (seed data)
A60: Rider (code) | B60: Age | C60: Coverage rule | D60: Other rules | E60: Rate / 1,000
A61: Accidental Death Benefit (RIDER_ADB), protection | B61: 18-65 | C61: Same as base | D61: - | E61: 0.85
A62: Permanent Disability (RIDER_DISABILITY), protection | B62: 18-60 | C62: Same as base | D62: - | E62: 1.10
A63: Term Rider Add-on (RIDER_TERM_ADDON), protection | B63: 21-55 | C63: Same as base | D63: - | E63: 1.25
A64: Critical Illness (RIDER_CRITICAL_ILLNESS), health | B64: 18-58 | C64: Percent of base, max 500,000 | D64: Health questionnaire | E64: 1.60
A65: Hospital Cash (RIDER_HOSPITAL_CASH), health | B65: 18-60 | C65: Fixed, max 100,000 | D65: - | E65: 0.65
A66: Waiver - Disability (RIDER_WAIVER_DISABILITY) | B66: 18-55 | C66: Same as base | D66: Exclusive group WAIVER_PREMIUM; base face >= 200,000 | E66: 0.70
A67: Waiver - Critical Illness (RIDER_WAIVER_CI) | B67: 18-55 | C67: Same as base | D67: Exclusive group WAIVER_PREMIUM; base face >= 200,000; health questionnaire | E67: 0.90
A68: Family Income Benefit (RIDER_FAMILY_INCOME), income | B68: 25-55 | C68: Percent of base, max 750,000 | D68: Base face >= 250,000 | E68: 1.35
A69: Guaranteed Income (RIDER_GUARANTEED_INCOME), income | B69: 30-60 | C69: Percent of base, max 500,000 | D69: Base face >= 300,000 | E69: 1.50
A71: 7. Confirmed routes (web)
A72: Route | B72: Page | C72: Note | E72: Source
A73: /login, /forgot-password, /reset-password-otp, /reset-password, /register, /verify-otp | B73: Guest pages | C73: OTP screens exist for password reset and agent registration (see observations) | E73: S
A74: /change-password, /dashboard, /applications, /applications/new, /applications/{id} | B74: Authenticated | C74: start page has application-create-draft-button | E74: S
A75: /applications/{id}/client, /address-contact, /kyc-financial, /product, /riders, /beneficiaries, /documents, /review, /confirmation, /status | B75: Workflow | C75: POST /applications/{id}/validate and /submit | E75: S
A76: /products, /products/{product}, /profile, /support, /admin/* | B76: Other | C76: Admin out of scope (Q-15) | E76: S
A78: 8. Observations to raise (not defects)
A79: Observation | B79: Why it matters | C79: Action | E79: Source
A80: Q-06 answer says no OTP/MFA, but the app has OTP screens for password reset and agent registration, and a seeded agent.mfa user | B80: Password-policy tests use /change-password to avoid OTP; confirm scope with mentor | C80: Confirm | E80: S, A
A81: Lab Manual sample uses test ids login-email / login-password / login-submit; the build uses login-email-input / login-password-input / login-submit-button | B81: Selectors from the manual would fail | C81: Use ids on Environment_Facts / Test_Cases | E81: M, S
A82: No explicit "Save draft" button: drafts are created on application-create-draft-button and saved by each Save & Continue | B82: WF-V01 wording adapted | C82: Confirm in UI | E82: S
A83: No status filter control seen on the dashboard markup; API supports ?status= | B83: DASH-V05 adapted | C83: Confirm in UI | E83: S
A84: Seeded references use 4-digit sequences (WL202605170001); generated ones use 5 digits | B84: Reference regex applies to newly submitted applications only | C84: Check at submit | E84: S
A85: The zip contains a docs folder with mentor/seeded-defect material and .bak files | B85: Black-box rule and your own findings: these were deliberately not used | C85: Decide with mentor whether to use | E85: S

Sheet Traceability_Risk
A1: Risk ID | B1: Module | C1: Risk | D1: Priority | E1: Seeded defect | F1: Layers | G1: Planned tests (doc 04) | H1: Test cases linked (live) | I1: Linked test cases (generated list) | J1: Coverage type | K1: Coverage status
A2: R-AUTH-01 | B2: Authentication | C2: Valid agent cannot log in after an authentication change; every journey is blocked. | D2: P1 | E2: SDC-01 | F2: UI · API | G2: AUTH-V01, API-P02 | H2: =COUNTIF(Test_Cases!$E$2:$E$200,"*"&A2&"*") -> 2 | I2: TC-AUTH-001, TC-API-010 | J2: Test cases | K2: =IF(H2>0,"Covered",IF(J2="Test cases","GAP - add test","Addressed outside test cases")) -> Covered
A3: R-AUTH-02 | B3: Authentication | C3: Locked agent sees a wrong or misleading message, or reaches the dashboard. | D3: P2 | E3: SDC-02 | F3: UI · API · DB | G3: AUTH-V06 | H3: =COUNTIF(Test_Cases!$E$2:$E$200,"*"&A3&"*") -> 2 | I3: TC-AUTH-006, TC-API-010 | J3: Test cases | K3: =IF(H3>0,"Covered",IF(J3="Test cases","GAP - add test","Addressed outside test cases")) -> Covered
A4: R-AUTH-03 | B4: Authentication | C4: Account does not lock after five failed attempts (or locks early/late). | D4: P2 | F4: UI · API · DB | G4: AUTH-V07 | H4: =COUNTIF(Test_Cases!$E$2:$E$200,"*"&A4&"*") -> 1 | I4: TC-AUTH-007 | J4: Test cases | K4: =IF(H4>0,"Covered",IF(J4="Test cases","GAP - add test","Addressed outside test cases")) -> Covered
A5: R-AUTH-04 | B5: Authentication | C5: Password policy inconsistent: weak passwords accepted, or UI and API rules differ. | D5: P2 | E5: SDC-03 | F5: UI · API | G5: AUTH-V08 | H5: =COUNTIF(Test_Cases!$E$2:$E$200,"*"&A5&"*") -> 1 | I5: TC-AUTH-008 | J5: Test cases | K5: =IF(H5>0,"Covered",IF(J5="Test cases","GAP - add test","Addressed outside test cases")) -> Covered
A6: R-AUTH-05 | B6: Authentication | C6: Invalid-password and blank-field messages are wrong or missing. | D6: P3 | F6: UI | G6: AUTH-V02, AUTH-V03 | H6: =COUNTIF(Test_Cases!$E$2:$E$200,"*"&A6&"*") -> 2 | I6: TC-AUTH-002, TC-AUTH-003 | J6: Test cases | K6: =IF(H6>0,"Covered",IF(J6="Test cases","GAP - add test","Addressed outside test cases")) -> Covered
A7: R-AUTH-06 | B7: Authentication | C7: Session survives logout, or protected routes and APIs are reachable without login. | D7: P2 | F7: UI · API | G7: AUTH-V04, AUTH-V05, API-V02 | H7: =COUNTIF(Test_Cases!$E$2:$E$200,"*"&A7&"*") -> 3 | I7: TC-AUTH-004, TC-AUTH-005, TC-API-002 | J7: Test cases | K7: =IF(H7>0,"Covered",IF(J7="Test cases","GAP - add test","Addressed outside test cases")) -> Covered
A8: R-AUTH-07 | B8: Authentication | C8: MFA/OTP flow cannot be automated reliably (unknown simulation mechanism). | D8: P3 | F8: UI | G8: Exploratory, AUTH extension | H8: =COUNTIF(Test_Cases!$E$2:$E$200,"*"&A8&"*") -> 0 | J8: Out of scope (Q-06) | K8: =IF(H8>0,"Covered",IF(J8="Test cases","GAP - add test","Addressed outside test cases")) -> Addressed outside test cases
A9: R-DASH-01 | B9: Dashboard | C9: Agent sees another agent's applications (data isolation breach). | D9: P2 | F9: UI · API · DB | G9: DASH-V02, API-V08 | H9: =COUNTIF(Test_Cases!$E$2:$E$200,"*"&A9&"*") -> 2 | I9: TC-DASH-002, TC-API-008 | J9: Test cases | K9: =IF(H9>0,"Covered",IF(J9="Test cases","GAP - add test","Addressed outside test cases")) -> Covered
A10: R-DASH-02 | B10: Dashboard | C10: Dashboard status differs from backend / detail-page status. | D10: P1 | E10: SDC-18 | F10: UI · API · DB | G10: DASH-V06, WF-V07, API-V06 | H10: =COUNTIF(Test_Cases!$E$2:$E$200,"*"&A10&"*") -> 4 | I10: TC-DASH-006, TC-WF-006, TC-WF-007, TC-API-006 | J10: Test cases | K10: =IF(H10>0,"Covered",IF(J10="Test cases","GAP - add test","Addressed outside test cases")) -> Covered
A11: R-DASH-03 | B11: Dashboard | C11: Resume opens a wrong or blank application. | D11: P2 | E11: SDC-16 | F11: UI · DB | G11: DASH-V04 | H11: =COUNTIF(Test_Cases!$E$2:$E$200,"*"&A11&"*") -> 1 | I11: TC-DASH-004 | J11: Test cases | K11: =IF(H11>0,"Covered",IF(J11="Test cases","GAP - add test","Addressed outside test cases")) -> Covered
A12: R-DASH-04 | B12: Dashboard | C12: Status filters return wrong rows; new-agent empty state broken. | D12: P3 | F12: UI | G12: DASH-V03, DASH-V05 | H12: =COUNTIF(Test_Cases!$E$2:$E$200,"*"&A12&"*") -> 3 | I12: TC-DASH-001, TC-DASH-003, TC-DASH-005 | J12: Test cases | K12: =IF(H12>0,"Covered",IF(J12="Test cases","GAP - add test","Addressed outside test cases")) -> Covered
A13: R-CLI-01 | B13: Client information | C13: Age eligibility (18-65) not enforced, or boundary off by one. | D13: P1 | E13: SDC-04 | F13: UI · API | G13: CLI-V03, CLI-V04, CLI-P01, API-V03 | H13: =COUNTIF(Test_Cases!$E$2:$E$200,"*"&A13&"*") -> 4 | I13: TC-CLI-003, TC-CLI-004, TC-CLI-006, TC-API-003 | J13: Test cases | K13: =IF(H13>0,"Covered",IF(J13="Test cases","GAP - add test","Addressed outside test cases")) -> Covered
A14: R-CLI-02 | B14: Client information | C14: Future date of birth accepted and persisted. | D14: P2 | E14: SDC-05 | F14: UI · API · DB | G14: CLI-V05, API-V03 | H14: =COUNTIF(Test_Cases!$E$2:$E$200,"*"&A14&"*") -> 2 | I14: TC-CLI-005, TC-API-003 | J14: Test cases | K14: =IF(H14>0,"Covered",IF(J14="Test cases","GAP - add test","Addressed outside test cases")) -> Covered
A15: R-CLI-03 | B15: Client information | C15: Mandatory personal fields can be left blank. | D15: P3 | F15: UI · API | G15: CLI-V02 | H15: =COUNTIF(Test_Cases!$E$2:$E$200,"*"&A15&"*") -> 3 | I15: TC-CLI-001, TC-CLI-002, TC-CLI-008 | J15: Test cases | K15: =IF(H15>0,"Covered",IF(J15="Test cases","GAP - add test","Addressed outside test cases")) -> Covered
A16: R-CLI-04 | B16: Client information | C16: Age calculation wrong around birthdays, leap years or timezone. | D16: P3 | F16: UI | G16: CLI-P02 | H16: =COUNTIF(Test_Cases!$E$2:$E$200,"*"&A16&"*") -> 1 | I16: TC-CLI-007 | J16: Test cases | K16: =IF(H16>0,"Covered",IF(J16="Test cases","GAP - add test","Addressed outside test cases")) -> Covered
A17: R-CLI-05 | B17: Client information | C17: Saved client data differs between UI and API/database after save. | D17: P2 | F17: UI · API · DB | G17: CLI-V01, API client GET | H17: =COUNTIF(Test_Cases!$E$2:$E$200,"*"&A17&"*") -> 1 | I17: TC-CLI-001 | J17: Test cases | K17: =IF(H17>0,"Covered",IF(J17="Test cases","GAP - add test","Addressed outside test cases")) -> Covered
A18: R-ADR-01 | B18: Address & contact | C18: Same-as-residential copies wrongly or goes stale after later edits. | D18: P3 | F18: UI | G18: CLI-V06 | H18: =COUNTIF(Test_Cases!$E$2:$E$200,"*"&A18&"*") -> 1 | I18: TC-ADR-001 | J18: Test cases | K18: =IF(H18>0,"Covered",IF(J18="Test cases","GAP - add test","Addressed outside test cases")) -> Covered
A19: R-ADR-02 | B19: Address & contact | C19: Invalid email, phone or postal code accepted. | D19: P3 | F19: UI · API | G19: CLI-V07, ADR-P01 | H19: =COUNTIF(Test_Cases!$E$2:$E$200,"*"&A19&"*") -> 3 | I19: TC-ADR-002, TC-ADR-003, TC-ADR-004 | J19: Test cases | K19: =IF(H19>0,"Covered",IF(J19="Test cases","GAP - add test","Addressed outside test cases")) -> Covered
A20: R-ADR-03 | B20: Address & contact | C20: Mailing address or preferred communication mode not enforced. | D20: P3 | F20: UI | G20: ADR-P02, ADR-P03 | H20: =COUNTIF(Test_Cases!$E$2:$E$200,"*"&A20&"*") -> 2 | I20: TC-ADR-005, TC-ADR-006 | J20: Test cases | K20: =IF(H20>0,"Covered",IF(J20="Test cases","GAP - add test","Addressed outside test cases")) -> Covered
A21: R-KYC-01 | B21: KYC & compliance | C21: SSN / ID shown unmasked on entry, review, confirmation or in API payload. | D21: P1 | E21: SDC-07 | F21: UI · API · DB | G21: CLI-V08 | H21: =COUNTIF(Test_Cases!$E$2:$E$200,"*"&A21&"*") -> 1 | I21: TC-KYC-001 | J21: Test cases | K21: =IF(H21>0,"Covered",IF(J21="Test cases","GAP - add test","Addressed outside test cases")) -> Covered
A22: R-KYC-02 | B22: KYC & compliance | C22: Mandatory KYC documents not enforced before submission. | D22: P1 | E22: SDC-06 | F22: UI · API | G22: DOC-V04, API-V05 | H22: =COUNTIF(Test_Cases!$E$2:$E$200,"*"&A22&"*") -> 2 | I22: TC-DOC-004, TC-API-005 | J22: Test cases | K22: =IF(H22>0,"Covered",IF(J22="Test cases","GAP - add test","Addressed outside test cases")) -> Covered
A23: R-KYC-03 | B23: KYC & compliance | C23: Income vs premium affordability check not applied. | D23: P1 | E23: SDC-08 | F23: UI · API | G23: KYC-P01 | H23: =COUNTIF(Test_Cases!$E$2:$E$200,"*"&A23&"*") -> 1 | I23: TC-KYC-004 | J23: Test cases | K23: =IF(H23>0,"Covered",IF(J23="Test cases","GAP - add test","Addressed outside test cases")) -> Covered
A24: R-KYC-04 | B24: KYC & compliance | C24: ID number validation does not change with ID type. | D24: P3 | F24: UI · API | G24: KYC-P02 | H24: =COUNTIF(Test_Cases!$E$2:$E$200,"*"&A24&"*") -> 1 | I24: TC-KYC-005 | J24: Test cases | K24: =IF(H24>0,"Covered",IF(J24="Test cases","GAP - add test","Addressed outside test cases")) -> Covered
A25: R-KYC-05 | B25: KYC & compliance | C25: PEP = Yes does not require details; incomplete declaration does not block. | D25: P2 | F25: UI · API · DB | G25: CLI-V10, KYC-P03 | H25: =COUNTIF(Test_Cases!$E$2:$E$200,"*"&A25&"*") -> 2 | I25: TC-KYC-003, TC-KYC-006 | J25: Test cases | K25: =IF(H25>0,"Covered",IF(J25="Test cases","GAP - add test","Addressed outside test cases")) -> Covered
A26: R-PROD-01 | B26: Product & policy | C26: Product eligibility / suitability not validated against age or financial profile. | D26: P1 | E26: SDC-09 | F26: UI · API | G26: PROD-V07 | H26: =COUNTIF(Test_Cases!$E$2:$E$200,"*"&A26&"*") -> 1 | I26: TC-PROD-007 | J26: Test cases | K26: =IF(H26>0,"Covered",IF(J26="Test cases","GAP - add test","Addressed outside test cases")) -> Covered
A27: R-PROD-02 | B27: Product & policy | C27: Face value minimum / maximum not enforced. | D27: P2 | F27: UI · API | G27: PROD-V03, PROD-V04 | H27: =COUNTIF(Test_Cases!$E$2:$E$200,"*"&A27&"*") -> 2 | I27: TC-PROD-003, TC-PROD-004 | J27: Test cases | K27: =IF(H27>0,"Covered",IF(J27="Test cases","GAP - add test","Addressed outside test cases")) -> Covered
A28: R-PROD-03 | B28: Product & policy | C28: Premium does not recalculate after frequency, face value or term change. | D28: P1 | E28: SDC-12 | F28: UI · API | G28: PROD-V05 | H28: =COUNTIF(Test_Cases!$E$2:$E$200,"*"&A28&"*") -> 1 | I28: TC-PROD-005 | J28: Test cases | K28: =IF(H28>0,"Covered",IF(J28="Test cases","GAP - add test","Addressed outside test cases")) -> Covered
A29: R-PROD-04 | B29: Product & policy | C29: Review-page premium differs from configuration-page premium. | D29: P2 | E29: SDC-12 | F29: UI · API · DB | G29: PROD-V06 | H29: =COUNTIF(Test_Cases!$E$2:$E$200,"*"&A29&"*") -> 1 | I29: TC-PROD-006 | J29: Test cases | K29: =IF(H29>0,"Covered",IF(J29="Test cases","GAP - add test","Addressed outside test cases")) -> Covered
A30: R-PROD-05 | B30: Product & policy | C30: Catalog shows wrong or inactive products; detail page differs from API. | D30: P3 | F30: UI · API | G30: PROD-V01, PROD-V02, API-V01, API-V07 | H30: =COUNTIF(Test_Cases!$E$2:$E$200,"*"&A30&"*") -> 4 | I30: TC-PROD-001, TC-PROD-002, TC-API-001, TC-API-007 | J30: Test cases | K30: =IF(H30>0,"Covered",IF(J30="Test cases","GAP - add test","Addressed outside test cases")) -> Covered
A31: R-PROD-06 | B31: Product & policy | C31: Payment-term / policy-term options not constrained by product rules. | D31: P3 | F31: UI · API | G31: PROD-V01..V07 (extension) | H31: =COUNTIF(Test_Cases!$E$2:$E$200,"*"&A31&"*") -> 1 | I31: TC-PROD-002 | J31: Test cases | K31: =IF(H31>0,"Covered",IF(J31="Test cases","GAP - add test","Addressed outside test cases")) -> Covered
A32: R-RID-01 | B32: Riders | C32: Rider coverage allowed to exceed base policy face value. | D32: P1 | E32: SDC-10 | F32: UI · API | G32: RIDER-V02 | H32: =COUNTIF(Test_Cases!$E$2:$E$200,"*"&A32&"*") -> 1 | I32: TC-RID-002 | J32: Test cases | K32: =IF(H32>0,"Covered",IF(J32="Test cases","GAP - add test","Addressed outside test cases")) -> Covered
A33: R-RID-02 | B33: Riders | C33: Mutually exclusive waiver riders can both be selected. | D33: P2 | E33: SDC-11 | F33: UI · API | G33: RIDER-V05 | H33: =COUNTIF(Test_Cases!$E$2:$E$200,"*"&A33&"*") -> 1 | I33: TC-RID-005 | J33: Test cases | K33: =IF(H33>0,"Covered",IF(J33="Test cases","GAP - add test","Addressed outside test cases")) -> Covered
A34: R-RID-03 | B34: Riders | C34: Age-ineligible rider can be added. | D34: P2 | F34: UI · API | G34: RIDER-V03 | H34: =COUNTIF(Test_Cases!$E$2:$E$200,"*"&A34&"*") -> 1 | I34: TC-RID-003 | J34: Test cases | K34: =IF(H34>0,"Covered",IF(J34="Test cases","GAP - add test","Addressed outside test cases")) -> Covered
A35: R-RID-04 | B35: Riders | C35: Maximum rider count not enforced. | D35: P3 | F35: UI · API | G35: RIDER-V04 | H35: =COUNTIF(Test_Cases!$E$2:$E$200,"*"&A35&"*") -> 1 | I35: TC-RID-004 | J35: Test cases | K35: =IF(H35>0,"Covered",IF(J35="Test cases","GAP - add test","Addressed outside test cases")) -> Covered
A36: R-RID-05 | B36: Riders | C36: Rider premium not itemized or total premium not updated. | D36: P2 | E36: SDC-12 | F36: UI · API | G36: RIDER-V01, RIDER-V07 | H36: =COUNTIF(Test_Cases!$E$2:$E$200,"*"&A36&"*") -> 2 | I36: TC-RID-001, TC-RID-007 | J36: Test cases | K36: =IF(H36>0,"Covered",IF(J36="Test cases","GAP - add test","Addressed outside test cases")) -> Covered
A37: R-RID-06 | B37: Riders | C37: Critical illness rider does not trigger health questionnaire. | D37: P3 | F37: UI | G37: RIDER-V06 | H37: =COUNTIF(Test_Cases!$E$2:$E$200,"*"&A37&"*") -> 1 | I37: TC-RID-006 | J37: Test cases | K37: =IF(H37>0,"Covered",IF(J37="Test cases","GAP - add test","Addressed outside test cases")) -> Covered
A38: R-BEN-01 | B38: Beneficiaries | C38: Allocation below or above 100% allowed (primary and secondary). | D38: P1 | E38: SDC-13 | F38: UI · API | G38: BEN-V02, BEN-V03, BEN-V04, API-V04 | H38: =COUNTIF(Test_Cases!$E$2:$E$200,"*"&A38&"*") -> 4 | I38: TC-BEN-002, TC-BEN-003, TC-BEN-004, TC-API-004 | J38: Test cases | K38: =IF(H38>0,"Covered",IF(J38="Test cases","GAP - add test","Addressed outside test cases")) -> Covered
A39: R-BEN-02 | B39: Beneficiaries | C39: Minor beneficiary accepted without guardian details. | D39: P1 | E39: SDC-14 | F39: UI · API | G39: BEN-V05 | H39: =COUNTIF(Test_Cases!$E$2:$E$200,"*"&A39&"*") -> 1 | I39: TC-BEN-005 | J39: Test cases | K39: =IF(H39>0,"Covered",IF(J39="Test cases","GAP - add test","Addressed outside test cases")) -> Covered
A40: R-BEN-03 | B40: Beneficiaries | C40: Duplicate (Name + DOB + Relationship) not blocked. | D40: P2 | E40: SDC-15 | F40: UI · API · DB | G40: BEN-V08 | H40: =COUNTIF(Test_Cases!$E$2:$E$200,"*"&A40&"*") -> 1 | I40: TC-BEN-008 | J40: Test cases | K40: =IF(H40>0,"Covered",IF(J40="Test cases","GAP - add test","Addressed outside test cases")) -> Covered
A41: R-BEN-04 | B41: Beneficiaries | C41: Running total not updated on edit / remove; dynamic rows mishandled. | D41: P3 | F41: UI | G41: BEN-V09 | H41: =COUNTIF(Test_Cases!$E$2:$E$200,"*"&A41&"*") -> 2 | I41: TC-BEN-001, TC-BEN-009 | J41: Test cases | K41: =IF(H41>0,"Covered",IF(J41="Test cases","GAP - add test","Addressed outside test cases")) -> Covered
A42: R-BEN-05 | B42: Beneficiaries | C42: Trust / Organization specific fields missing or not mandatory. | D42: P3 | F42: UI · API | G42: BEN-V06, BEN-V07 | H42: =COUNTIF(Test_Cases!$E$2:$E$200,"*"&A42&"*") -> 2 | I42: TC-BEN-006, TC-BEN-007 | J42: Test cases | K42: =IF(H42>0,"Covered",IF(J42="Test cases","GAP - add test","Addressed outside test cases")) -> Covered
A43: R-BEN-06 | B43: Beneficiaries | C43: Missing primary beneficiary does not block; irrevocable confirmation modal absent. | D43: P2 | F43: UI · API | G43: BEN-V01 (extension) | H43: =COUNTIF(Test_Cases!$E$2:$E$200,"*"&A43&"*") -> 2 | I43: TC-BEN-001, TC-DOC-005 | J43: Test cases | K43: =IF(H43>0,"Covered",IF(J43="Test cases","GAP - add test","Addressed outside test cases")) -> Covered
A44: R-DOC-01 | B44: Documents | C44: Unsupported file type or oversized file accepted. | D44: P3 | F44: UI · API · DB | G44: DOC-V02, DOC-V03, API-P01 | H44: =COUNTIF(Test_Cases!$E$2:$E$200,"*"&A44&"*") -> 4 | I44: TC-KYC-002, TC-DOC-002, TC-DOC-003, TC-API-009 | J44: Test cases | K44: =IF(H44>0,"Covered",IF(J44="Test cases","GAP - add test","Addressed outside test cases")) -> Covered
A45: R-DOC-02 | B45: Documents | C45: Valid upload shows success but is not stored or linked to the application. | D45: P2 | F45: UI · API · DB | G45: DOC-V01 | H45: =COUNTIF(Test_Cases!$E$2:$E$200,"*"&A45&"*") -> 2 | I45: TC-DOC-001, TC-API-009 | J45: Test cases | K45: =IF(H45>0,"Covered",IF(J45="Test cases","GAP - add test","Addressed outside test cases")) -> Covered
A46: R-DOC-03 | B46: Documents | C46: Validation summary incomplete, or its links do not navigate to the field. | D46: P3 | F46: UI | G46: VAL-V01, VAL-V02 | H46: =COUNTIF(Test_Cases!$E$2:$E$200,"*"&A46&"*") -> 2 | I46: TC-DOC-005, TC-DOC-006 | J46: Test cases | K46: =IF(H46>0,"Covered",IF(J46="Test cases","GAP - add test","Addressed outside test cases")) -> Covered
A47: R-WF-01 | B47: Submission & status | C47: Draft data not saved or restored correctly. | D47: P1 | E47: SDC-16 | F47: UI · API · DB | G47: WF-V01, WF-V02 | H47: =COUNTIF(Test_Cases!$E$2:$E$200,"*"&A47&"*") -> 2 | I47: TC-WF-001, TC-WF-002 | J47: Test cases | K47: =IF(H47>0,"Covered",IF(J47="Test cases","GAP - add test","Addressed outside test cases")) -> Covered
A48: R-WF-02 | B48: Submission & status | C48: Submit enabled while critical validation errors exist. | D48: P1 | E48: SDC-17 | F48: UI · API | G48: VAL-V03, API-V05 | H48: =COUNTIF(Test_Cases!$E$2:$E$200,"*"&A48&"*") -> 2 | I48: TC-DOC-007, TC-API-005 | J48: Test cases | K48: =IF(H48>0,"Covered",IF(J48="Test cases","GAP - add test","Addressed outside test cases")) -> Covered
A49: R-WF-03 | B49: Submission & status | C49: Valid submission fails, reference number missing or duplicated, or status not transitioned. | D49: P2 | F49: UI · API · DB | G49: WF-V03, WF-V06 | H49: =COUNTIF(Test_Cases!$E$2:$E$200,"*"&A49&"*") -> 2 | I49: TC-WF-003, TC-WF-006 | J49: Test cases | K49: =IF(H49>0,"Covered",IF(J49="Test cases","GAP - add test","Addressed outside test cases")) -> Covered
A50: R-WF-04 | B50: Submission & status | C50: Submitted application remains editable. | D50: P2 | F50: UI · API | G50: WF-V04 | H50: =COUNTIF(Test_Cases!$E$2:$E$200,"*"&A50&"*") -> 1 | I50: TC-WF-004 | J50: Test cases | K50: =IF(H50>0,"Covered",IF(J50="Test cases","GAP - add test","Addressed outside test cases")) -> Covered
A51: R-WF-05 | B51: Submission & status | C51: Confirmation message or status text missing after submission. | D51: P3 | F51: UI | G51: WF-V05 | H51: =COUNTIF(Test_Cases!$E$2:$E$200,"*"&A51&"*") -> 1 | I51: TC-WF-005 | J51: Test cases | K51: =IF(H51>0,"Covered",IF(J51="Test cases","GAP - add test","Addressed outside test cases")) -> Covered
A52: R-API-01 | B52: API | C52: API validation differs from UI validation (rules enforced in one layer only). | D52: P1 | E52: SDC-19 | F52: UI · API | G52: API-V03, API-V04, API-V05 | H52: =COUNTIF(Test_Cases!$E$2:$E$200,"*"&A52&"*") -> 3 | I52: TC-API-003, TC-API-004, TC-API-005 | J52: Test cases | K52: =IF(H52>0,"Covered",IF(J52="Test cases","GAP - add test","Addressed outside test cases")) -> Covered
A53: R-API-02 | B53: API | C53: API reachable without valid token/session, or token handling inconsistent. | D53: P2 | F53: API | G53: API-V02 | H53: =COUNTIF(Test_Cases!$E$2:$E$200,"*"&A53&"*") -> 1 | I53: TC-API-002 | J53: Test cases | K53: =IF(H53>0,"Covered",IF(J53="Test cases","GAP - add test","Addressed outside test cases")) -> Covered
A54: R-API-03 | B54: API | C54: Schema or status-code contract drift (missing keys, wrong codes). | D54: P3 | F54: API | G54: API-V01, API-V07 | H54: =COUNTIF(Test_Cases!$E$2:$E$200,"*"&A54&"*") -> 2 | I54: TC-API-001, TC-API-007 | J54: Test cases | K54: =IF(H54>0,"Covered",IF(J54="Test cases","GAP - add test","Addressed outside test cases")) -> Covered
A55: R-ENV-01 | B55: Data & environment | C55: Seed data drift or shared state: tests mutate seeded data or collide with other runs. | D55: P2 | F55: DB · UI | G55: All stateful tests | H55: =COUNTIF(Test_Cases!$E$2:$E$200,"*"&A55&"*") -> 0 | J55: Framework / CI design | K55: =IF(H55>0,"Covered",IF(J55="Test cases","GAP - add test","Addressed outside test cases")) -> Addressed outside test cases
A56: R-ENV-02 | B56: Data & environment | C56: Lab VM / app unavailable (RDP delay, app down) causing false failures. | D56: P3 | F56: Environment | G56: Global setup health check | H56: =COUNTIF(Test_Cases!$E$2:$E$200,"*"&A56&"*") -> 0 | J56: Framework / CI design | K56: =IF(H56>0,"Covered",IF(J56="Test cases","GAP - add test","Addressed outside test cases")) -> Addressed outside test cases
A57: R-ENV-03 | B57: Data & environment | C57: Hosted CI runner cannot reach an app bound to 127.0.0.1 on the lab VM. | D57: P2 | F57: CI | G57: CI pipeline | H57: =COUNTIF(Test_Cases!$E$2:$E$200,"*"&A57&"*") -> 0 | J57: Framework / CI design | K57: =IF(H57>0,"Covered",IF(J57="Test cases","GAP - add test","Addressed outside test cases")) -> Addressed outside test cases
A58: R-ENV-04 | B58: Data & environment | C58: Credentials or tokens leak into repo, reports, screenshots or traces. | D58: P2 | F58: All | G58: Config and reporting | H58: =COUNTIF(Test_Cases!$E$2:$E$200,"*"&A58&"*") -> 0 | J58: Framework / CI design | K58: =IF(H58>0,"Covered",IF(J58="Test cases","GAP - add test","Addressed outside test cases")) -> Addressed outside test cases
A59: R-FW-01 | B59: Framework | C59: Failures hard to debug because evidence is captured inconsistently. | D59: P3 | E59: SDC-20 | F59: Framework | G59: Playwright config | H59: =COUNTIF(Test_Cases!$E$2:$E$200,"*"&A59&"*") -> 0 | J59: Framework / CI design | K59: =IF(H59>0,"Covered",IF(J59="Test cases","GAP - add test","Addressed outside test cases")) -> Addressed outside test cases
A60: R-FW-02 | B60: Framework | C60: Flaky tests from dynamic sections, hardcoded waits or weak locators. | D60: P2 | F60: UI | G60: All UI tests | H60: =COUNTIF(Test_Cases!$E$2:$E$200,"*"&A60&"*") -> 0 | J60: Framework / CI design | K60: =IF(H60>0,"Covered",IF(J60="Test cases","GAP - add test","Addressed outside test cases")) -> Addressed outside test cases
A61: R-FW-03 | B61: Framework | C61: Failures misclassified (e.g. UI/API mismatch logged as defect without matching user scope; concurrency-only failures treated as blockers). | D61: P2 | F61: All | G61: Defect triage process | H61: =COUNTIF(Test_Cases!$E$2:$E$200,"*"&A61&"*") -> 0 | J61: Framework / CI design | K61: =IF(H61>0,"Covered",IF(J61="Test cases","GAP - add test","Addressed outside test cases")) -> Addressed outside test cases
A62: R-FW-04 | B62: Framework | C62: Locators and test data built on assumptions that the VM walkthrough later disproves. | D62: P2 | F62: UI · API | G62: All | H62: =COUNTIF(Test_Cases!$E$2:$E$200,"*"&A62&"*") -> 0 | J62: Framework / CI design | K62: =IF(H62>0,"Covered",IF(J62="Test cases","GAP - add test","Addressed outside test cases")) -> Addressed outside test cases
A63: R-FW-05 | B63: Framework | C63: Traceability gaps between risks, test cases and defects. | D63: P3 | F63: All | G63: Test design sheet | H63: =COUNTIF(Test_Cases!$E$2:$E$200,"*"&A63&"*") -> 0 | J63: Framework / CI design | K63: =IF(H63>0,"Covered",IF(J63="Test cases","GAP - add test","Addressed outside test cases")) -> Addressed outside test cases

Sheet Traceability_SDC
A1: Candidate ID | B1: Seeded defect candidate (Problem Statement 2.2) | C1: Risk ID(s) | D1: Layers | E1: Test cases linked (live) | F1: Linked test cases (generated list) | G1: Detection approach | H1: Official catalog ID | I1: Coverage status
A2: SDC-01 | B2: Valid agents unable to log in after authentication changes | C2: R-AUTH-01 | D2: UI, API | E2: =COUNTIF(Test_Cases!$F$2:$F$200,"*"&A2&"*") -> 2 | F2: TC-AUTH-001, TC-API-010 | G2: Login with each seeded valid agent; compare API status code with UI outcome | I2: =IF(E2>0,"Covered","Framework configuration") -> Covered
A3: SDC-02 | B3: Locked agents receive incorrect or misleading error messages | C3: R-AUTH-02 | D3: UI, API, DB | E3: =COUNTIF(Test_Cases!$F$2:$F$200,"*"&A3&"*") -> 2 | F3: TC-AUTH-006, TC-API-010 | G3: Assert exact locked-account message and no dashboard access; check lock flag | I3: =IF(E3>0,"Covered","Framework configuration") -> Covered
A4: SDC-03 | B4: Password policy not consistently enforced | C4: R-AUTH-04 | D4: UI, API | E4: =COUNTIF(Test_Cases!$F$2:$F$200,"*"&A4&"*") -> 1 | F4: TC-AUTH-008 | G4: Weak-password matrix on reset/change; repeat through API | I4: =IF(E4>0,"Covered","Framework configuration") -> Covered
A5: SDC-04 | B5: Client age eligibility rules missed | C5: R-CLI-01 | D5: UI, API | E5: =COUNTIF(Test_Cases!$F$2:$F$200,"*"&A5&"*") -> 4 | F5: TC-CLI-003, TC-CLI-004, TC-CLI-006, TC-API-003 | G5: Boundary DOBs (17y364d, 18y, 65y, 65y+1d) | I5: =IF(E5>0,"Covered","Framework configuration") -> Covered
A6: SDC-05 | B6: Future date of birth accepted | C6: R-CLI-02 | D6: UI, API, DB | E6: =COUNTIF(Test_Cases!$F$2:$F$200,"*"&A6&"*") -> 2 | F6: TC-CLI-005, TC-API-003 | G6: Future DOB via UI and API; confirm nothing persisted | I6: =IF(E6>0,"Covered","Framework configuration") -> Covered
A7: SDC-06 | B7: Mandatory KYC documents not enforced before submission | C7: R-KYC-02 | D7: UI, API | E7: =COUNTIF(Test_Cases!$F$2:$F$200,"*"&A7&"*") -> 2 | F7: TC-DOC-004, TC-API-005 | G7: Submit without documents; expect block in UI and API | I7: =IF(E7>0,"Covered","Framework configuration") -> Covered
A8: SDC-07 | B8: SSN / sensitive identification data not masked | C8: R-KYC-01 | D8: UI, API, DB | E8: =COUNTIF(Test_Cases!$F$2:$F$200,"*"&A8&"*") -> 1 | F8: TC-KYC-001 | G8: Check entry, review page, confirmation page and API payload | I8: =IF(E8>0,"Covered","Framework configuration") -> Covered
A9: SDC-08 | B9: Income vs premium affordability validation not applied | C9: R-KYC-03 | D9: UI, API | E9: =COUNTIF(Test_Cases!$F$2:$F$200,"*"&A9&"*") -> 1 | F9: TC-KYC-004 | G9: Low income + high premium; expect warning or block | I9: =IF(E9>0,"Covered","Framework configuration") -> Covered
A10: SDC-09 | B10: Product eligibility not validated against age / financial suitability | C10: R-PROD-01 | D10: UI, API | E10: =COUNTIF(Test_Cases!$F$2:$F$200,"*"&A10&"*") -> 1 | F10: TC-PROD-007 | G10: Unsuitable risk profile / out-of-range age; expect warning | I10: =IF(E10>0,"Covered","Framework configuration") -> Covered
A11: SDC-10 | B11: Rider coverage allowed to exceed base policy face value | C11: R-RID-01 | D11: UI, API | E11: =COUNTIF(Test_Cases!$F$2:$F$200,"*"&A11&"*") -> 1 | F11: TC-RID-002 | G11: Rider amount > face value; expect validation | I11: =IF(E11>0,"Covered","Framework configuration") -> Covered
A12: SDC-11 | B12: Mutually exclusive waiver riders can both be selected | C12: R-RID-02 | D12: UI, API | E12: =COUNTIF(Test_Cases!$F$2:$F$200,"*"&A12&"*") -> 1 | F12: TC-RID-005 | G12: Select both waiver riders; expect second blocked | I12: =IF(E12>0,"Covered","Framework configuration") -> Covered
A13: SDC-12 | B13: Premium calculation does not update after configuration changes | C13: R-PROD-03, R-RID-05 | D13: UI, API | E13: =COUNTIF(Test_Cases!$F$2:$F$200,"*"&A13&"*") -> 3 | F13: TC-PROD-005, TC-PROD-006, TC-RID-007 | G13: Change frequency / face value / rider; compare premium before and after, UI vs API | I13: =IF(E13>0,"Covered","Framework configuration") -> Covered
... A21: SDC-20 | B21: Test failures hard to debug (evidence not captured consistently) | C21: R-FW-01 | D21: Framework | E21: =COUNTIF(Test_Cases!$F$2:$F$200,"*"&A21&"*") -> 0 | F21: (framework configuration) | G21: Not an app defect: solved by trace/screenshot/video/log config (Submission 2) | I21: =IF(E21>0,"Covered","Framework configuration") -> Framework configuration
A23: Q-03: no catalog is given to the cohort. These 20 are candidates taken from Problem Statement 2.2; confirm each by execution and record the result in the defect log (Q-17: report expected seeded AND unexpected defects).

Sheet Coverage_Summary
A1: Coverage Summary
A2: Actual counts are live formulas on Test_Cases. Minimum (Submission and Evaluation 5.5) and Planned (QA Plan section 8) are blue inputs. Q-16: full scope kept; priority marks the order.
A4: Module | B4: Minimum | C4: Planned | D4: Actual | E4: Actual vs minimum | F4: Actual vs planned | G4: Note
A5: Authentication | B5: 6 | C5: 8 | D5: =COUNTIF(Test_Cases!$B$2:$B$200,A5) -> 8 | E5: =D5-B5 -> 2 | F5: =D5-C5 -> 0 | G5: =IF(D5>=B5,"Meets minimum","Below minimum") -> Meets minimum
A6: Dashboard & application summary | B6: 4 | C6: 6 | D6: =COUNTIF(Test_Cases!$B$2:$B$200,A6) -> 6 | E6: =D6-B6 -> 2 | F6: =D6-C6 -> 0 | G6: =IF(D6>=B6,"Meets minimum","Below minimum") -> Meets minimum
A7: Client / insured information | B7: 8 | C7: 8 | D7: =COUNTIF(Test_Cases!$B$2:$B$200,A7) -> 8 | E7: =D7-B7 -> 0 | F7: =D7-C7 -> 0 | G7: =IF(D7>=B7,"Meets minimum","Below minimum") -> Meets minimum
A8: Address & contact | B8: 5 | C8: 6 | D8: =COUNTIF(Test_Cases!$B$2:$B$200,A8) -> 6 | E8: =D8-B8 -> 1 | F8: =D8-C8 -> 0 | G8: =IF(D8>=B8,"Meets minimum","Below minimum") -> Meets minimum
A9: KYC, financial & compliance | B9: 6 | C9: 6 | D9: =COUNTIF(Test_Cases!$B$2:$B$200,A9) -> 6 | E9: =D9-B9 -> 0 | F9: =D9-C9 -> 0 | G9: =IF(D9>=B9,"Meets minimum","Below minimum") -> Meets minimum
A10: Product selection & policy config | B10: 6 | C10: 7 | D10: =COUNTIF(Test_Cases!$B$2:$B$200,A10) -> 7 | E10: =D10-B10 -> 1 | F10: =D10-C10 -> 0 | G10: =IF(D10>=B10,"Meets minimum","Below minimum") -> Meets minimum
A11: Rider selection | B11: 5 | C11: 7 | D11: =COUNTIF(Test_Cases!$B$2:$B$200,A11) -> 7 | E11: =D11-B11 -> 2 | F11: =D11-C11 -> 0 | G11: =IF(D11>=B11,"Meets minimum","Below minimum") -> Meets minimum
A12: Beneficiary management | B12: 7 | C12: 9 | D12: =COUNTIF(Test_Cases!$B$2:$B$200,A12) -> 9 | E12: =D12-B12 -> 2 | F12: =D12-C12 -> 0 | G12: =IF(D12>=B12,"Meets minimum","Below minimum") -> Meets minimum
A13: Document upload & validation summary | B13: 4 | C13: 7 | D13: =COUNTIF(Test_Cases!$B$2:$B$200,A13) -> 7 | E13: =D13-B13 -> 3 | F13: =D13-C13 -> 0 | G13: =IF(D13>=B13,"Meets minimum","Below minimum") -> Meets minimum
A14: Submission & status tracking | B14: 5 | C14: 7 | D14: =COUNTIF(Test_Cases!$B$2:$B$200,A14) -> 7 | E14: =D14-B14 -> 2 | F14: =D14-C14 -> 0 | G14: =IF(D14>=B14,"Meets minimum","Below minimum") -> Meets minimum
A15: API tests | B15: 8 | C15: 10 | D15: =COUNTIF(Test_Cases!$B$2:$B$200,A15) -> 10 | E15: =D15-B15 -> 2 | F15: =D15-C15 -> 0 | G15: =IF(D15>=B15,"Meets minimum","Below minimum") -> Meets minimum
A16: Total | B16: =SUM(B5:B15) -> 64 | C16: =SUM(C5:C15) -> 81 | D16: =SUM(D5:D15) -> 81 | E16: =D16-B16 -> 17 | F16: =D16-C16 -> 0 | G16: =IF(D16>=B16,"Meets minimum","Below minimum") -> Meets minimum
A18: By priority | B18: Count | C18: % of total
A19: P1 | B19: =COUNTIF(Test_Cases!$I$2:$I$200,"P1") -> 35 | C19: =IF($D$16=0,0,B19/$D$16) -> 0.43209877
A20: P2 | B20: =COUNTIF(Test_Cases!$I$2:$I$200,"P2") -> 21 | C20: =IF($D$16=0,0,B20/$D$16) -> 0.25925926
A21: P3 | B21: =COUNTIF(Test_Cases!$I$2:$I$200,"P3") -> 25 | C21: =IF($D$16=0,0,B21/$D$16) -> 0.30864198
A23: By layer | B23: Count | C23: % of total
A24: UI | B24: =COUNTIF(Test_Cases!$G$2:$G$200,"UI") -> 41 | C24: =IF($D$16=0,0,B24/$D$16) -> 0.50617284
A25: API | B25: =COUNTIF(Test_Cases!$G$2:$G$200,"API") -> 8 | C25: =IF($D$16=0,0,B25/$D$16) -> 0.098765432
A26: UI + API | B26: =COUNTIF(Test_Cases!$G$2:$G$200,"UI + API") -> 32 | C26: =IF($D$16=0,0,B26/$D$16) -> 0.39506173
A28: By test type | B28: Count | C28: % of total
A29: Smoke | B29: =COUNTIF(Test_Cases!$H$2:$H$200,"Smoke") -> 10 | C29: =IF($D$16=0,0,B29/$D$16) -> 0.12345679
A30: Functional | B30: =COUNTIF(Test_Cases!$H$2:$H$200,"Functional") -> 17 | C30: =IF($D$16=0,0,B30/$D$16) -> 0.20987654
A31: Negative | B31: =COUNTIF(Test_Cases!$H$2:$H$200,"Negative") -> 29 | C31: =IF($D$16=0,0,B31/$D$16) -> 0.35802469
A32: Boundary | B32: =COUNTIF(Test_Cases!$H$2:$H$200,"Boundary") -> 13 | C32: =IF($D$16=0,0,B32/$D$16) -> 0.16049383
A33: Reconciliation | B33: =COUNTIF(Test_Cases!$H$2:$H$200,"Reconciliation") -> 8 | C33: =IF($D$16=0,0,B33/$D$16) -> 0.098765432
A34: Authorization | B34: =COUNTIF(Test_Cases!$H$2:$H$200,"Authorization") -> 3 | C34: =IF($D$16=0,0,B34/$D$16) -> 0.037037037
A35: E2E | B35: =COUNTIF(Test_Cases!$H$2:$H$200,"E2E") -> 1 | C35: =IF($D$16=0,0,B35/$D$16) -> 0.012345679
A37: By tag (a test can carry several) | B37: Count | C37: % of total
A38: @smoke | B38: =COUNTIF(Test_Cases!$K$2:$K$200,"*@smoke*") -> 11 | C38: =IF($D$16=0,0,B38/$D$16) -> 0.13580247
A39: @regression | B39: =COUNTIF(Test_Cases!$K$2:$K$200,"*@regression*") -> 81 | C39: =IF($D$16=0,0,B39/$D$16) -> 1
A40: @e2e | B40: =COUNTIF(Test_Cases!$K$2:$K$200,"*@e2e*") -> 1 | C40: =IF($D$16=0,0,B40/$D$16) -> 0.012345679
A41: @api | B41: =COUNTIF(Test_Cases!$K$2:$K$200,"*@api*") -> 40 | C41: =IF($D$16=0,0,B41/$D$16) -> 0.49382716
A43: By automation status | B43: Count | C43: % of total
A44: Ready | B44: =COUNTIF(Test_Cases!$U$2:$U$200,"Ready") -> 68 | C44: =IF($D$16=0,0,B44/$D$16) -> 0.83950617
A45: Needs confirmation | B45: =COUNTIF(Test_Cases!$U$2:$U$200,"Needs confirmation") -> 13 | C45: =IF($D$16=0,0,B45/$D$16) -> 0.16049383
A46: Automated | B46: =COUNTIF(Test_Cases!$U$2:$U$200,"Automated") -> 0 | C46: =IF($D$16=0,0,B46/$D$16) -> 0
A47: Manual only | B47: =COUNTIF(Test_Cases!$U$2:$U$200,"Manual only") -> 0 | C47: =IF($D$16=0,0,B47/$D$16) -> 0
A49: By execution status | B49: Count | C49: % of total
A50: Not run | B50: =COUNTIF(Test_Cases!$V$2:$V$200,"Not run") -> 81 | C50: =IF($D$16=0,0,B50/$D$16) -> 1
A51: Pass | B51: =COUNTIF(Test_Cases!$V$2:$V$200,"Pass") -> 0 | C51: =IF($D$16=0,0,B51/$D$16) -> 0
A52: Fail | B52: =COUNTIF(Test_Cases!$V$2:$V$200,"Fail") -> 0 | C52: =IF($D$16=0,0,B52/$D$16) -> 0
A53: Blocked | B53: =COUNTIF(Test_Cases!$V$2:$V$200,"Blocked") -> 0 | C53: =IF($D$16=0,0,B53/$D$16) -> 0
A54: Skipped | B54: =COUNTIF(Test_Cases!$V$2:$V$200,"Skipped") -> 0 | C54: =IF($D$16=0,0,B54/$D$16) -> 0
A56: By defect type (failed tests) | B56: Count | C56: % of total
A57: Expected seeded (candidate) | B57: =COUNTIF(Test_Cases!$X$2:$X$200,"Expected seeded (candidate)") -> 0 | C57: =IF($D$16=0,0,B57/$D$16) -> 0
A58: Unexpected | B58: =COUNTIF(Test_Cases!$X$2:$X$200,"Unexpected") -> 0 | C58: =IF($D$16=0,0,B58/$D$16) -> 0
A59: Automation issue | B59: =COUNTIF(Test_Cases!$X$2:$X$200,"Automation issue") -> 0 | C59: =IF($D$16=0,0,B59/$D$16) -> 0
A60: Environment/data | B60: =COUNTIF(Test_Cases!$X$2:$X$200,"Environment/data") -> 0 | C60: =IF($D$16=0,0,B60/$D$16) -> 0
A62: Traceability checks | B62: Covered | C62: Total | D62: Gaps
A63: P1 risks with at least one test case | B63: =COUNTIFS(Traceability_Risk!$D$2:$D$63,"P1",Traceability_Risk!$H$2:$H$63,">0") -> 14 | C63: =COUNTIF(Traceability_Risk!$D$2:$D$63,"P1") -> 14 | D63: =C63-B63 -> 0
A64: Risks of type "Test cases" covered | B64: =COUNTIFS(Traceability_Risk!$J$2:$J$63,"Test cases",Traceability_Risk!$H$2:$H$63,">0") -> 52 | C64: =COUNTIF(Traceability_Risk!$J$2:$J$63,"Test cases") -> 52 | D64: =C64-B64 -> 0
A65: Candidate seeded defects with a test case | B65: =COUNTIF(Traceability_SDC!$E$2:$E$21,">0") -> 19 | C65: =COUNTA(Traceability_SDC!$A$2:$A$21) -> 20 | D65: =C65-B65 -> 1
A67: SDC-20 (evidence capture) is handled in Playwright config, not by a test. R-AUTH-07 (MFA/OTP) is out of scope (Q-06).

Sheet Open_Items
A1: Item | B1: Open item | C1: Related Q | D1: What we now know | E1: Status | F1: Tests still affected (live) | G1: Remaining action
A2: OI-01 | B2: Insurance app base URL / port | C2: Q-01 | D2: Port 8081 (A, M): http://<vm-ip>:8081 | E2: Closed | F2: =COUNTIF(Test_Cases!$S$2:$S$200,"*"&A2&"*") -> 0 | G2: Set INSURANCE_BASE_URL in .env
A3: OI-02 | B3: Seeded users per role | C3: Q-05 | D3: Users and learner pool listed in Lab Manual 3.1 (M). MFA and admin users out of scope. | E3: Closed | F3: =COUNTIF(Test_Cases!$S$2:$S$200,"*"&A3&"*") -> 0 | G3: Pick {learnerUser} and confirm {disposableAgent} with mentor
A4: OI-03 | B4: MFA/OTP mechanism | C4: Q-06 | D4: Answer: no MFA/OTP flow. Source has OTP for password reset and registration only. | E4: Out of scope | F4: =COUNTIF(Test_Cases!$S$2:$S$200,"*"&A4&"*") -> 0 | G4: Confirm OTP screens are out of scope
A5: OI-04 | B5: Database access (optional DB checks) | C5: Q-07 | D5: MySQL per app config; .sql dump found in db-dumps (A, S). API remains the default state check. | E5: In progress | F5: =COUNTIF(Test_Cases!$S$2:$S$200,"*"&A5&"*") -> 0 | G5: Check whether read-only MySQL access exists on the VM
A6: OI-05 | B6: API contract and setup | C6: Q-08 | D6: Static X-API-Key, agent_email scoping, POST /api/applications, envelope (S). See Environment_Facts section 3. | E6: Closed | F6: =COUNTIF(Test_Cases!$S$2:$S$200,"*"&A6&"*") -> 0 | G6: Confirm request payload names at first run
A7: OI-06 | B7: Age rule and message | C7: Q-09 | D7: 18 to 65 inclusive; message "Client age must be between 18 and 65 years." (A, S) | E7: Closed | F7: =COUNTIF(Test_Cases!$S$2:$S$200,"*"&A7&"*") -> 0 | G7: Confirm in UI where the message appears
A8: OI-07 | B8: Face value limits and terms | C8: Q-09 | D8: Limits per product and term options known (S). | E8: Closed | F8: =COUNTIF(Test_Cases!$S$2:$S$200,"*"&A8&"*") -> 0 | G8: Confirm against product-range-help text
A9: OI-08 | B9: Rider rules | C9: Q-09 | D9: Max 4; age ranges; exclusive waiver pair; caps; base minimums (S). | E9: Closed | F9: =COUNTIF(Test_Cases!$S$2:$S$200,"*"&A9&"*") -> 0 | G9: -
A10: OI-09 | B10: Upload rules | C10: Q-09 | D10: PDF/JPG/PNG, 5 MB, required KYC_ID (S). | E10: In progress | F10: =COUNTIF(Test_Cases!$S$2:$S$200,"*"&A10&"*") -> 1 | G10: Check PHP upload_max_filesize / post_max_size >= 5 MB
A11: OI-10 | B11: Password policy | C11: Q-09 | D11: Full rule list known (S). | E11: Closed | F11: =COUNTIF(Test_Cases!$S$2:$S$200,"*"&A11&"*") -> 0 | G11: -
A12: OI-11 | B12: Affordability and suitability | C12: Q-09 | D12: Affordability 20% of income (S). Suitability text and risk-profile rule not stated. | E12: In progress | F12: =COUNTIF(Test_Cases!$S$2:$S$200,"*"&A12&"*") -> 2 | G12: Capture suitability message; confirm annualised premium comparison
A13: OI-12 | B13: Reference number and statuses | C13: Q-09 | D13: WL + yyyymmdd + 5 digits; statuses listed (S). Approved and later out of scope. | E13: Closed | F13: =COUNTIF(Test_Cases!$S$2:$S$200,"*"&A13&"*") -> 0 | G13: -
... A19: OI-18 | B19: API error bodies | C19: Doc 05 B4 | D19: Status codes and envelopes known (S). Field-level error keys to capture. | E19: In progress | F19: =COUNTIF(Test_Cases!$S$2:$S$200,"*"&A19&"*") -> 2 | G19: Capture bodies at first run

Sheet Change_Log
A1: Ref | B1: Source | C1: Change | D1: Test cases affected
A2: C-01 | B2: Answer Q-01 | C2: Insurance app is on port 8081. Base URL variable INSURANCE_BASE_URL. | D2: All
A3: C-02 | B3: Answer Q-02 | C3: Playwright with TypeScript confirmed. | D3: All
A4: C-03 | B4: Answer Q-03, Q-17 | C4: No seeded-defect catalog is provided. SDC-01..SDC-20 remain candidates; added "Defect type (if Fail)" so expected-seeded and unexpected defects are reported separately. | D4: All (new column)
A5: C-04 | B5: Answer Q-04 | C5: Submission 1 format is the reference; no external template. | D5: -
A6: C-05 | B6: Lab Manual 3.1, Q-05, Q-10 | C6: Usernames filled in Test_Data; {lockedAgent} = agent.locked@insurance.test. Passwords and API key stay in .env. | D6: AUTH-*, DASH-*, API-*
A7: C-06 | B7: Answer Q-06 | C7: MFA/OTP out of scope; R-AUTH-07 closed. Observation: OTP screens exist for reset/registration, so password-policy checks use /change-password. | D7: AUTH-V08
A8: C-07 | B8: Answer Q-08 + zip | C8: API contract applied: static X-API-Key (not a token), agent_email scoping, POST /api/login, POST /api/applications for setup, 401 "Unauthorized" without key. Replaced "replay old token" step with session-cookie reuse. | D8: AUTH-V04, API-V01..V08, API-P01, API-P02
A9: C-08 | B9: Answer Q-09 + zip | C9: Limits and rules applied: age 18-65 inclusive, products and riders tables, max 4 riders, exclusive waivers, 20% affordability, 5 MB PDF/JPG/PNG, password policy, US phone/ZIP/state, reference format, premium formula. | D9: CLI-*, ADR-*, KYC-*, PROD-*, RIDER-*, DOC-*, WF-V03
A10: C-09 | B10: Answer Q-11, Q-15 | C10: Session timeout, admin and Approved status excluded. DASH-V05 now checks Draft/Submitted and API ?status=; Approved removed. | D10: DASH-V05
A11: C-10 | B11: Answer Q-12 | C11: Chromium default; Firefox/WebKit via config. | D11: -
A12: C-11 | B12: Answer Q-13 | C12: Build GitHub Actions workflow, run manually from the VM, document the limitation (R-ENV-03 decision). | D12: -
... A19: C-18 | B19: Process note | C19: While reading validation code I saw seeded-defect switch names. They are not used or listed in this workbook, and the seeded-defect seeder, .bak files and docs folder were not opened. | D19: -

Sheet Locator_Map
A1: Page (view) | B1: Route | C1: Page object | D1: data-testid | E1: Dynamic?
A2: address-contact/edit | B2: /applications/{id}/address-contact | C2: AddressContactPage | D2: address-contact-form
A3: address-contact/edit | B3: /applications/{id}/address-contact | C3: AddressContactPage | D3: address-contact-page
A4: address-contact/edit | B4: /applications/{id}/address-contact | C4: AddressContactPage | D4: address-contact-save-continue-button
A5: address-contact/edit | B5: /applications/{id}/address-contact | C5: AddressContactPage | D5: address-same-as-residential-checkbox
A6: address-contact/edit | B6: /applications/{id}/address-contact | C6: AddressContactPage | D6: contact-alternate-phone-input
A7: address-contact/edit | B7: /applications/{id}/address-contact | C7: AddressContactPage | D7: contact-mobile-number-input
A8: address-contact/edit | B8: /applications/{id}/address-contact | C8: AddressContactPage | D8: contact-preferred-mode-select
A9: address-contact/edit | B9: /applications/{id}/address-contact | C9: AddressContactPage | D9: contact-primary-email-input
A10: address-contact/edit | B10: /applications/{id}/address-contact | C10: AddressContactPage | D10: mailing-address-line-1-input
A11: address-contact/edit | B11: /applications/{id}/address-contact | C11: AddressContactPage | D11: mailing-address-line-2-input
A12: address-contact/edit | B12: /applications/{id}/address-contact | C12: AddressContactPage | D12: mailing-city-input
A13: address-contact/edit | B13: /applications/{id}/address-contact | C13: AddressContactPage | D13: mailing-postal-code-input
... A20: applications/index | B20: /applications | C20: DashboardPage | D20: application-new-button
A21: applications/index | B21: /applications | C21: DashboardPage | D21: application-open-{id} | E21: Yes
A22: applications/index | B22: /applications | C22: DashboardPage | D22: application-row-{id} | E22: Yes
A23: applications/index | B23: /applications | C23: DashboardPage | D23: applications-index-page
A24: applications/index | B24: /applications | C24: DashboardPage | D24: applications-table
A25: applications/show | B25: /applications/{id} | C25: Shared / n.a. | D25: application-summary-page
A26: applications/show | B26: /applications/{id} | C26: Shared / n.a. | D26: application-total-premium
A27: applications/start | B27: /applications/new | C27: DashboardPage | D27: application-create-draft-button
A28: applications/start | B28: /applications/new | C28: DashboardPage | D28: application-start-cancel-link
A29: applications/start | B29: /applications/new | C29: DashboardPage | D29: application-start-form
A30: applications/start | B30: /applications/new | C30: DashboardPage | D30: application-start-page
A31: auth/change-password | B31: /change-password | C31: LoginPage (account) | D31: change-password-confirm
A32: auth/change-password | B32: /change-password | C32: LoginPage (account) | D32: change-password-current
A33: auth/change-password | B33: /change-password | C33: LoginPage (account) | D33: change-password-form
A34: auth/change-password | B34: /change-password | C34: LoginPage (account) | D34: change-password-logout
... A80: beneficiaries/edit | B80: /applications/{id}/beneficiaries (edit mode) | C80: BeneficiaryPage | D80: beneficiary-country-input
A81: beneficiaries/edit | B81: /applications/{id}/beneficiaries (edit mode) | C81: BeneficiaryPage | D81: beneficiary-delete-{id} | E81: Yes
A82: beneficiaries/edit | B82: /applications/{id}/beneficiaries (edit mode) | C82: BeneficiaryPage | D82: beneficiary-designation-select
A83: beneficiaries/edit | B83: /applications/{id}/beneficiaries (edit mode) | C83: BeneficiaryPage | D83: beneficiary-dob-input
A84: beneficiaries/edit | B84: /applications/{id}/beneficiaries (edit mode) | C84: BeneficiaryPage | D84: beneficiary-edit-{id} | E84: Yes
A85: beneficiaries/edit | B85: /applications/{id}/beneficiaries (edit mode) | C85: BeneficiaryPage | D85: beneficiary-email-input
A86: beneficiaries/edit | B86: /applications/{id}/beneficiaries (edit mode) | C86: BeneficiaryPage | D86: beneficiary-empty-state
A87: beneficiaries/edit | B87: /applications/{id}/beneficiaries (edit mode) | C87: BeneficiaryPage | D87: beneficiary-error-summary
A88: beneficiaries/edit | B88: /applications/{id}/beneficiaries (edit mode) | C88: BeneficiaryPage | D88: beneficiary-first-name-input
A89: beneficiaries/edit | B89: /applications/{id}/beneficiaries (edit mode) | C89: BeneficiaryPage | D89: beneficiary-form
A90: beneficiaries/edit | B90: /applications/{id}/beneficiaries (edit mode) | C90: BeneficiaryPage | D90: beneficiary-gender-select
A91: beneficiaries/edit | B91: /applications/{id}/beneficiaries (edit mode) | C91: BeneficiaryPage | D91: beneficiary-guardian-address-input
A92: beneficiaries/edit | B92: /applications/{id}/beneficiaries (edit mode) | C92: BeneficiaryPage | D92: beneficiary-guardian-contact-input
A93: beneficiaries/edit | B93: /applications/{id}/beneficiaries (edit mode) | C93: BeneficiaryPage | D93: beneficiary-guardian-name-input
A94: beneficiaries/edit | B94: /applications/{id}/beneficiaries (edit mode) | C94: BeneficiaryPage | D94: beneficiary-guardian-relationship-input
A95: beneficiaries/edit | B95: /applications/{id}/beneficiaries (edit mode) | C95: BeneficiaryPage | D95: beneficiary-irrevocable-badge-{id} | E95: Yes
A96: beneficiaries/edit | B96: /applications/{id}/beneficiaries (edit mode) | C96: BeneficiaryPage | D96: beneficiary-last-name-input
A97: beneficiaries/edit | B97: /applications/{id}/beneficiaries (edit mode) | C97: BeneficiaryPage | D97: beneficiary-legal-acknowledgement-checkbox
A98: beneficiaries/edit | B98: /applications/{id}/beneficiaries (edit mode) | C98: BeneficiaryPage | D98: beneficiary-level-select
A99: beneficiaries/edit | B99: /applications/{id}/beneficiaries (edit mode) | C99: BeneficiaryPage | D99: beneficiary-locked-{id} | E99: Yes
A100: beneficiaries/edit | B100: /applications/{id}/beneficiaries (edit mode) | C100: BeneficiaryPage | D100: beneficiary-middle-name-input
A101: beneficiaries/edit | B101: /applications/{id}/beneficiaries (edit mode) | C101: BeneficiaryPage | D101: beneficiary-organization-contact-input
A102: beneficiaries/edit | B102: /applications/{id}/beneficiaries (edit mode) | C102: BeneficiaryPage | D102: beneficiary-organization-name-input
A103: beneficiaries/edit | B103: /applications/{id}/beneficiaries (edit mode) | C103: BeneficiaryPage | D103: beneficiary-organization-registration-input
A104: beneficiaries/edit | B104: /applications/{id}/beneficiaries (edit mode) | C104: BeneficiaryPage | D104: beneficiary-page
A105: beneficiaries/edit | B105: /applications/{id}/beneficiaries (edit mode) | C105: BeneficiaryPage | D105: beneficiary-phone-input
A106: beneficiaries/edit | B106: /applications/{id}/beneficiaries (edit mode) | C106: BeneficiaryPage | D106: beneficiary-postal-code-input
A107: beneficiaries/edit | B107: /applications/{id}/beneficiaries (edit mode) | C107: BeneficiaryPage | D107: beneficiary-relationship-select
A108: beneficiaries/edit | B108: /applications/{id}/beneficiaries (edit mode) | C108: BeneficiaryPage | D108: beneficiary-revocable-badge-{id} | E108: Yes
A109: beneficiaries/edit | B109: /applications/{id}/beneficiaries (edit mode) | C109: BeneficiaryPage | D109: beneficiary-row-{id} | E109: Yes
A110: beneficiaries/edit | B110: /applications/{id}/beneficiaries (edit mode) | C110: BeneficiaryPage | D110: beneficiary-save-button
A111: beneficiaries/edit | B111: /applications/{id}/beneficiaries (edit mode) | C111: BeneficiaryPage | D111: beneficiary-state-input
A112: beneficiaries/edit | B112: /applications/{id}/beneficiaries (edit mode) | C112: BeneficiaryPage | D112: beneficiary-table
A113: beneficiaries/edit | B113: /applications/{id}/beneficiaries (edit mode) | C113: BeneficiaryPage | D113: beneficiary-trust-date-input
A114: beneficiaries/edit | B114: /applications/{id}/beneficiaries (edit mode) | C114: BeneficiaryPage | D114: beneficiary-trust-name-input
A115: beneficiaries/edit | B115: /applications/{id}/beneficiaries (edit mode) | C115: BeneficiaryPage | D115: beneficiary-trustee-contact-input
A116: beneficiaries/edit | B116: /applications/{id}/beneficiaries (edit mode) | C116: BeneficiaryPage | D116: beneficiary-trustee-name-input
A117: beneficiaries/edit | B117: /applications/{id}/beneficiaries (edit mode) | C117: BeneficiaryPage | D117: beneficiary-type-select
A118: beneficiaries/edit | B118: /applications/{id}/beneficiaries (edit mode) | C118: BeneficiaryPage | D118: estate-assignment-fallback-message
A119: beneficiaries/edit | B119: /applications/{id}/beneficiaries (edit mode) | C119: BeneficiaryPage | D119: minor-guardian-section
A120: beneficiaries/index | B120: /applications/{id}/beneficiaries | C120: BeneficiaryPage | D120: beneficiary-address-line-1-input
A121: beneficiaries/index | B121: /applications/{id}/beneficiaries | C121: BeneficiaryPage | D121: beneficiary-allocation-input
... A126: beneficiaries/index | B126: /applications/{id}/beneficiaries | C126: BeneficiaryPage | D126: beneficiary-country-input
A127: beneficiaries/index | B127: /applications/{id}/beneficiaries | C127: BeneficiaryPage | D127: beneficiary-delete-{id} | E127: Yes
A128: beneficiaries/index | B128: /applications/{id}/beneficiaries | C128: BeneficiaryPage | D128: beneficiary-designation-select
A129: beneficiaries/index | B129: /applications/{id}/beneficiaries | C129: BeneficiaryPage | D129: beneficiary-dob-input
A130: beneficiaries/index | B130: /applications/{id}/beneficiaries | C130: BeneficiaryPage | D130: beneficiary-edit-{id} | E130: Yes
A131: beneficiaries/index | B131: /applications/{id}/beneficiaries | C131: BeneficiaryPage | D131: beneficiary-email-input
A132: beneficiaries/index | B132: /applications/{id}/beneficiaries | C132: BeneficiaryPage | D132: beneficiary-empty-state
A133: beneficiaries/index | B133: /applications/{id}/beneficiaries | C133: BeneficiaryPage | D133: beneficiary-error-summary
A134: beneficiaries/index | B134: /applications/{id}/beneficiaries | C134: BeneficiaryPage | D134: beneficiary-first-name-input
A135: beneficiaries/index | B135: /applications/{id}/beneficiaries | C135: BeneficiaryPage | D135: beneficiary-form
A136: beneficiaries/index | B136: /applications/{id}/beneficiaries | C136: BeneficiaryPage | D136: beneficiary-gender-select
A137: beneficiaries/index | B137: /applications/{id}/beneficiaries | C137: BeneficiaryPage | D137: beneficiary-guardian-address-input
A138: beneficiaries/index | B138: /applications/{id}/beneficiaries | C138: BeneficiaryPage | D138: beneficiary-guardian-contact-input
A139: beneficiaries/index | B139: /applications/{id}/beneficiaries | C139: BeneficiaryPage | D139: beneficiary-guardian-name-input
A140: beneficiaries/index | B140: /applications/{id}/beneficiaries | C140: BeneficiaryPage | D140: beneficiary-guardian-relationship-input
A141: beneficiaries/index | B141: /applications/{id}/beneficiaries | C141: BeneficiaryPage | D141: beneficiary-irrevocable-badge-{id} | E141: Yes
A142: beneficiaries/index | B142: /applications/{id}/beneficiaries | C142: BeneficiaryPage | D142: beneficiary-last-name-input
A143: beneficiaries/index | B143: /applications/{id}/beneficiaries | C143: BeneficiaryPage | D143: beneficiary-legal-acknowledgement-checkbox
A144: beneficiaries/index | B144: /applications/{id}/beneficiaries | C144: BeneficiaryPage | D144: beneficiary-level-select
A145: beneficiaries/index | B145: /applications/{id}/beneficiaries | C145: BeneficiaryPage | D145: beneficiary-locked-{id} | E145: Yes
A146: beneficiaries/index | B146: /applications/{id}/beneficiaries | C146: BeneficiaryPage | D146: beneficiary-middle-name-input
A147: beneficiaries/index | B147: /applications/{id}/beneficiaries | C147: BeneficiaryPage | D147: beneficiary-organization-contact-input
A148: beneficiaries/index | B148: /applications/{id}/beneficiaries | C148: BeneficiaryPage | D148: beneficiary-organization-name-input
A149: beneficiaries/index | B149: /applications/{id}/beneficiaries | C149: BeneficiaryPage | D149: beneficiary-organization-registration-input
A150: beneficiaries/index | B150: /applications/{id}/beneficiaries | C150: BeneficiaryPage | D150: beneficiary-page
A151: beneficiaries/index | B151: /applications/{id}/beneficiaries | C151: BeneficiaryPage | D151: beneficiary-phone-input
A152: beneficiaries/index | B152: /applications/{id}/beneficiaries | C152: BeneficiaryPage | D152: beneficiary-postal-code-input
A153: beneficiaries/index | B153: /applications/{id}/beneficiaries | C153: BeneficiaryPage | D153: beneficiary-relationship-select
A154: beneficiaries/index | B154: /applications/{id}/beneficiaries | C154: BeneficiaryPage | D154: beneficiary-revocable-badge-{id} | E154: Yes
A155: beneficiaries/index | B155: /applications/{id}/beneficiaries | C155: BeneficiaryPage | D155: beneficiary-row-{id} | E155: Yes
...
